{
"instructions_readme": "1) Open Chrome, 2) go to chrome://tracing, 3) click Load, 4) navigate to this file.",

"traceEvents":[
{ "pid": 1, "tid": 1, "ph": "M", "name": "thread_name", "args": { "name": "" } },
{ "pid": 1, "tid": 1, "ts": 2.19999998807907, "dur": 1731908.81347656, "ph": "X", "name": "il2cpp.exe", "args": { "durationMS": 1731.90881347656, "detail": "" } },
{ "pid": 1, "tid": 1, "ts": 101338.806152344, "dur": 1629821.04492188, "ph": "X", "name": "Build", "args": { "durationMS": 1629.82104492188, "detail": "" } },
{ "pid": 1, "tid": 1, "ts": 131211.486816406, "dur": 1598653.80859375, "ph": "X", "name": "BuildBinary", "args": { "durationMS": 1598.65380859375, "detail": "" } },
{ "pid": 1, "tid": 1, "ts": 131569.198608398, "dur": 5556.79988861084, "ph": "X", "name": "ToolChain OnBeforeCompile Build", "args": { "durationMS": 5.55679988861084, "detail": "" } },
{ "pid": 1, "tid": 1, "ts": 137275.405883789, "dur": 105763.198852539, "ph": "X", "name": "FindFilesToCompile", "args": { "durationMS": 105.763198852539, "detail": "" } },
{ "pid": 1, "tid": 1, "ts": 243038.803100586, "dur": 868923.278808594, "ph": "X", "name": "Calculate header hashes", "args": { "durationMS": 868.923278808594, "detail": "" } },
{ "pid": 1, "tid": 1, "ts": 245035.217285156, "dur": 44044.7998046875, "ph": "X", "name": "HashOfAllFilesWithProviderExtensionInDirectory", "args": { "durationMS": 44.0447998046875, "detail": "E:\\Graduate\\Graduate Design\\GitHub\\CSAR\\CSAR Simulation\\Build\\06\\Il2CppOutputProject\\IL2CPP\\libil2cpp" } },
{ "pid": 1, "tid": 1, "ts": 289130.187988281, "dur": 4149.89995956421, "ph": "X", "name": "HashOfAllFilesWithProviderExtensionInDirectory", "args": { "durationMS": 4.14989995956421, "detail": "E:\\Graduate\\Graduate Design\\GitHub\\CSAR\\CSAR Simulation\\Build\\06\\Il2CppOutputProject\\IL2CPP\\external\\bdwgc\\include" } },
{ "pid": 1, "tid": 1, "ts": 293311.798095703, "dur": 1430.19998073578, "ph": "X", "name": "HashOfAllFilesWithProviderExtensionInDirectory", "args": { "durationMS": 1.43019998073578, "detail": "E:\\Graduate\\Graduate Design\\GitHub\\CSAR\\CSAR Simulation\\Build\\06\\Il2CppOutputProject\\Source" } },
{ "pid": 1, "tid": 1, "ts": 297309.692382813, "dur": 32700.7026672363, "ph": "X", "name": "HashOfAllFilesWithProviderExtensionInDirectory", "args": { "durationMS": 32.7007026672363, "detail": "C:\\Program Files (x86)\\Microsoft Visual Studio\\2019\\Professional\\VC\\Tools\\MSVC\\14.27.29110\\include" } },
{ "pid": 1, "tid": 1, "ts": 330076.904296875, "dur": 47916.9998168945, "ph": "X", "name": "HashOfAllFilesWithProviderExtensionInDirectory", "args": { "durationMS": 47.9169998168945, "detail": "C:\\Program Files (x86)\\Windows Kits\\10\\Include\\10.0.19041.0\\shared" } },
{ "pid": 1, "tid": 1, "ts": 378047.210693359, "dur": 347229.095458984, "ph": "X", "name": "HashOfAllFilesWithProviderExtensionInDirectory", "args": { "durationMS": 347.229095458984, "detail": "C:\\Program Files (x86)\\Windows Kits\\10\\Include\\10.0.19041.0\\um" } },
{ "pid": 1, "tid": 1, "ts": 725328.369140625, "dur": 304490.600585938, "ph": "X", "name": "HashOfAllFilesWithProviderExtensionInDirectory", "args": { "durationMS": 304.490600585938, "detail": "C:\\Program Files (x86)\\Windows Kits\\10\\Include\\10.0.19041.0\\winrt" } },
{ "pid": 1, "tid": 1, "ts": 1029870.84960938, "dur": 7265.79999923706, "ph": "X", "name": "HashOfAllFilesWithProviderExtensionInDirectory", "args": { "durationMS": 7.26579999923706, "detail": "C:\\Program Files (x86)\\Windows Kits\\10\\Include\\10.0.19041.0\\ucrt" } },
{ "pid": 1, "tid": 1, "ts": 1101803.10058594, "dur": 5906.09979629517, "ph": "X", "name": "HashOfAllFilesWithProviderExtensionInDirectory", "args": { "durationMS": 5.90609979629517, "detail": "E:\\Graduate\\Graduate Design\\GitHub\\CSAR\\CSAR Simulation\\Build\\06\\Il2CppOutputProject\\IL2CPP\\external\\bdwgc\\libatomic_ops\\src" } },
{ "pid": 1, "tid": 1, "ts": 1111962.64648438, "dur": 47801.7997741699, "ph": "X", "name": "Calculate lumped hashes", "args": { "durationMS": 47.8017997741699, "detail": "" } },
{ "pid": 1, "tid": 1, "ts": 1112790.64941406, "dur": 362.899988889694, "ph": "X", "name": "HashOfAllFilesWithProviderExtensionInDirectory", "args": { "durationMS": 0.362899988889694, "detail": "E:\\Graduate\\Graduate Design\\GitHub\\CSAR\\CSAR Simulation\\Build\\06\\Il2CppOutputProject\\IL2CPP\\libil2cpp\\codegen" } },
{ "pid": 1, "tid": 1, "ts": 1113171.63085938, "dur": 575.100004673004, "ph": "X", "name": "HashOfAllFilesWithProviderExtensionInDirectory", "args": { "durationMS": 0.575100004673004, "detail": "E:\\Graduate\\Graduate Design\\GitHub\\CSAR\\CSAR Simulation\\Build\\06\\Il2CppOutputProject\\IL2CPP\\libil2cpp\\gc" } },
{ "pid": 1, "tid": 1, "ts": 1113762.08496094, "dur": 14343.6994552612, "ph": "X", "name": "HashOfAllFilesWithProviderExtensionInDirectory", "args": { "durationMS": 14.3436994552612, "detail": "E:\\Graduate\\Graduate Design\\GitHub\\CSAR\\CSAR Simulation\\Build\\06\\Il2CppOutputProject\\IL2CPP\\libil2cpp\\icalls" } },
{ "pid": 1, "tid": 1, "ts": 1128131.22558594, "dur": 1254.19998168945, "ph": "X", "name": "HashOfAllFilesWithProviderExtensionInDirectory", "args": { "durationMS": 1.25419998168945, "detail": "E:\\Graduate\\Graduate Design\\GitHub\\CSAR\\CSAR Simulation\\Build\\06\\Il2CppOutputProject\\IL2CPP\\libil2cpp\\metadata" } },
{ "pid": 1, "tid": 1, "ts": 1129403.44238281, "dur": 754.199981689453, "ph": "X", "name": "HashOfAllFilesWithProviderExtensionInDirectory", "args": { "durationMS": 0.754199981689453, "detail": "E:\\Graduate\\Graduate Design\\GitHub\\CSAR\\CSAR Simulation\\Build\\06\\Il2CppOutputProject\\IL2CPP\\libil2cpp\\mono" } },
{ "pid": 1, "tid": 1, "ts": 1130174.07226563, "dur": 385.600000619888, "ph": "X", "name": "HashOfAllFilesWithProviderExtensionInDirectory", "args": { "durationMS": 0.385600000619888, "detail": "E:\\Graduate\\Graduate Design\\GitHub\\CSAR\\CSAR Simulation\\Build\\06\\Il2CppOutputProject\\IL2CPP\\libil2cpp\\mono-runtime" } },
{ "pid": 1, "tid": 1, "ts": 1130575.68359375, "dur": 13536.3006591797, "ph": "X", "name": "HashOfAllFilesWithProviderExtensionInDirectory", "args": { "durationMS": 13.5363006591797, "detail": "E:\\Graduate\\Graduate Design\\GitHub\\CSAR\\CSAR Simulation\\Build\\06\\Il2CppOutputProject\\IL2CPP\\libil2cpp\\os" } },
{ "pid": 1, "tid": 1, "ts": 1144136.35253906, "dur": 1382.50005245209, "ph": "X", "name": "HashOfAllFilesWithProviderExtensionInDirectory", "args": { "durationMS": 1.38250005245209, "detail": "E:\\Graduate\\Graduate Design\\GitHub\\CSAR\\CSAR Simulation\\Build\\06\\Il2CppOutputProject\\IL2CPP\\libil2cpp\\utils" } },
{ "pid": 1, "tid": 1, "ts": 1145538.20800781, "dur": 4217.00000762939, "ph": "X", "name": "HashOfAllFilesWithProviderExtensionInDirectory", "args": { "durationMS": 4.21700000762939, "detail": "E:\\Graduate\\Graduate Design\\GitHub\\CSAR\\CSAR Simulation\\Build\\06\\Il2CppOutputProject\\IL2CPP\\libil2cpp\\vm" } },
{ "pid": 1, "tid": 1, "ts": 1149775.63476563, "dur": 522.499978542328, "ph": "X", "name": "HashOfAllFilesWithProviderExtensionInDirectory", "args": { "durationMS": 0.522499978542328, "detail": "E:\\Graduate\\Graduate Design\\GitHub\\CSAR\\CSAR Simulation\\Build\\06\\Il2CppOutputProject\\IL2CPP\\libil2cpp\\vm-utils" } },
{ "pid": 1, "tid": 1, "ts": 1150315.18554688, "dur": 9440.50025939941, "ph": "X", "name": "HashOfAllFilesWithProviderExtensionInDirectory", "args": { "durationMS": 9.44050025939941, "detail": "E:\\Graduate\\Graduate Design\\GitHub\\CSAR\\CSAR Simulation\\Build\\06\\Il2CppOutputProject\\IL2CPP\\external\\bdwgc" } },
{ "pid": 1, "tid": 1, "ts": 1159764.52636719, "dur": 204976.501464844, "ph": "X", "name": "BuildAllCppFiles", "args": { "durationMS": 204.976501464844, "detail": "" } },
{ "pid": 1, "tid": 1, "ts": 1163364.74609375, "dur": 201375.793457031, "ph": "X", "name": "Compile", "args": { "durationMS": 201.375793457031, "detail": "" } },
{ "pid": 1, "tid": 1, "ts": 1364742.06542969, "dur": 1584.40005779266, "ph": "X", "name": "OnBeforeLink Build", "args": { "durationMS": 1.58440005779266, "detail": "" } },
{ "pid": 1, "tid": 1, "ts": 1365306.51855469, "dur": 1019.00005340576, "ph": "X", "name": "ProgramBuildDescription OnBeforeLink Build", "args": { "durationMS": 1.01900005340576, "detail": "" } },
{ "pid": 1, "tid": 1, "ts": 1366326.41601563, "dur": 186550.399780273, "ph": "X", "name": "Postprocess Object Files", "args": { "durationMS": 186.550399780273, "detail": "" } },
{ "pid": 1, "tid": 1, "ts": 1367551.7578125, "dur": 185324.401855469, "ph": "X", "name": "Link", "args": { "durationMS": 185.324401855469, "detail": "GameAssembly.dll" } },
{ "pid": 1, "tid": 1, "ts": 1552877.19726563, "dur": 526.49998664856, "ph": "X", "name": "ProgramDescription Finalize Build", "args": { "durationMS": 0.52649998664856, "detail": "" } },
{ "pid": 1, "tid": 1, "ts": 1553591.18652344, "dur": 176273.498535156, "ph": "X", "name": "Clean IL2CPP Cache", "args": { "durationMS": 176.273498535156, "detail": "" } },
{ "pid": 1, "tid": 12, "ph": "M", "name": "thread_name", "args": { "name": "" } },
{ "pid": 1, "tid": 12, "ts": 1173171.875, "dur": 29774.2023468018, "ph": "X", "name": "HashCompilerInvocation", "args": { "durationMS": 29.7742023468018, "detail": "Il2CppGenericClassTable.c" } },
{ "pid": 1, "tid": 12, "ts": 1202993.04199219, "dur": 12248.3997344971, "ph": "X", "name": "HashCompilerInvocation", "args": { "durationMS": 12.2483997344971, "detail": "GenericMethods7.cpp" } },
{ "pid": 1, "tid": 12, "ts": 1215283.44726563, "dur": 9022.00031280518, "ph": "X", "name": "HashCompilerInvocation", "args": { "durationMS": 9.02200031280518, "detail": "mscorlib8.cpp" } },
{ "pid": 1, "tid": 12, "ts": 1224344.7265625, "dur": 10363.3003234863, "ph": "X", "name": "HashCompilerInvocation", "args": { "durationMS": 10.3633003234863, "detail": "GenericMethods3.cpp" } },
{ "pid": 1, "tid": 12, "ts": 1234751.46484375, "dur": 9994.00043487549, "ph": "X", "name": "HashCompilerInvocation", "args": { "durationMS": 9.99400043487549, "detail": "mscorlib5.cpp" } },
{ "pid": 1, "tid": 12, "ts": 1244787.96386719, "dur": 9022.80044555664, "ph": "X", "name": "HashCompilerInvocation", "args": { "durationMS": 9.02280044555664, "detail": "UnityEngine.UI1.cpp" } },
{ "pid": 1, "tid": 12, "ts": 1253848.38867188, "dur": 15014.3995285034, "ph": "X", "name": "HashCompilerInvocation", "args": { "durationMS": 15.0143995285034, "detail": "Generics9.cpp" } },
{ "pid": 1, "tid": 12, "ts": 1268903.80859375, "dur": 7084.40017700195, "ph": "X", "name": "HashCompilerInvocation", "args": { "durationMS": 7.08440017700195, "detail": "Il2CppComCallableWrappers23.cpp" } },
{ "pid": 1, "tid": 12, "ts": 1276028.93066406, "dur": 7830.10005950928, "ph": "X", "name": "HashCompilerInvocation", "args": { "durationMS": 7.83010005950928, "detail": "Il2CppComCallableWrappers25.cpp" } },
{ "pid": 1, "tid": 12, "ts": 1283947.02148438, "dur": 7043.30015182495, "ph": "X", "name": "HashCompilerInvocation", "args": { "durationMS": 7.04330015182495, "detail": "Il2CppComCallableWrappers6.cpp" } },
{ "pid": 1, "tid": 12, "ts": 1291042.23632813, "dur": 7377.69985198975, "ph": "X", "name": "HashCompilerInvocation", "args": { "durationMS": 7.37769985198975, "detail": "Generics49.cpp" } },
{ "pid": 1, "tid": 12, "ts": 1298461.9140625, "dur": 6705.39999008179, "ph": "X", "name": "HashCompilerInvocation", "args": { "durationMS": 6.70539999008179, "detail": "Il2CppComCallableWrappers7.cpp" } },
{ "pid": 1, "tid": 12, "ts": 1305204.58984375, "dur": 6186.39993667603, "ph": "X", "name": "HashCompilerInvocation", "args": { "durationMS": 6.18639993667603, "detail": "Generics15.cpp" } },
{ "pid": 1, "tid": 12, "ts": 1311431.27441406, "dur": 6399.89995956421, "ph": "X", "name": "HashCompilerInvocation", "args": { "durationMS": 6.39989995956421, "detail": "Generics5.cpp" } },
{ "pid": 1, "tid": 12, "ts": 1317867.79785156, "dur": 4739.39990997314, "ph": "X", "name": "HashCompilerInvocation", "args": { "durationMS": 4.73939990997314, "detail": "I18N.West.cpp" } },
{ "pid": 1, "tid": 12, "ts": 1322646.11816406, "dur": 3267.69995689392, "ph": "X", "name": "HashCompilerInvocation", "args": { "durationMS": 3.26769995689392, "detail": "I18N.Other.cpp" } },
{ "pid": 1, "tid": 12, "ts": 1325950.43945313, "dur": 2352.40006446838, "ph": "X", "name": "HashCompilerInvocation", "args": { "durationMS": 2.35240006446838, "detail": "I18N.MidEast.cpp" } },
{ "pid": 1, "tid": 12, "ts": 1328344.48242188, "dur": 1820.39999961853, "ph": "X", "name": "HashCompilerInvocation", "args": { "durationMS": 1.82039999961853, "detail": "UnityEngine.ParticleSystemModule.cpp" } },
{ "pid": 1, "tid": 12, "ts": 1330220.94726563, "dur": 3320.39999961853, "ph": "X", "name": "HashCompilerInvocation", "args": { "durationMS": 3.32039999961853, "detail": "Mono.Security.cpp" } },
{ "pid": 1, "tid": 12, "ts": 1333604.24804688, "dur": 2460.29996871948, "ph": "X", "name": "HashCompilerInvocation", "args": { "durationMS": 2.46029996871948, "detail": "inflate.c" } },
{ "pid": 1, "tid": 12, "ts": 1336823.12011719, "dur": 1256.19995594025, "ph": "X", "name": "HashCompilerInvocation", "args": { "durationMS": 1.25619995594025, "detail": "UnityEngine.PhysicsModule_CodeGen.c" } },
{ "pid": 1, "tid": 12, "ts": 1338113.52539063, "dur": 3064.59999084473, "ph": "X", "name": "HashCompilerInvocation", "args": { "durationMS": 3.06459999084473, "detail": "I18N_CodeGen.c" } },
{ "pid": 1, "tid": 12, "ts": 1341657.34863281, "dur": 1092.9000377655, "ph": "X", "name": "HashCompilerInvocation", "args": { "durationMS": 1.0929000377655, "detail": "UnityEngine.AIModule.cpp" } },
{ "pid": 1, "tid": 12, "ts": 1342785.27832031, "dur": 2240.00000953674, "ph": "X", "name": "HashCompilerInvocation", "args": { "durationMS": 2.24000000953674, "detail": "UnityEngine.SharedInternalsModule_CodeGen.c" } },
{ "pid": 1, "tid": 12, "ts": 1345085.08300781, "dur": 1968.50001811981, "ph": "X", "name": "HashCompilerInvocation", "args": { "durationMS": 1.96850001811981, "detail": "DOTween46_CodeGen.c" } },
{ "pid": 1, "tid": 12, "ts": 1347102.41699219, "dur": 1887.69996166229, "ph": "X", "name": "HashCompilerInvocation", "args": { "durationMS": 1.88769996166229, "detail": "zutil.c" } },
{ "pid": 1, "tid": 12, "ts": 1349033.32519531, "dur": 4503.60012054443, "ph": "X", "name": "HashCompilerInvocation", "args": { "durationMS": 4.50360012054443, "detail": "UnityEngine.VFXModule_CodeGen.c" } },
{ "pid": 1, "tid": 12, "ts": 1353586.42578125, "dur": 1579.39994335175, "ph": "X", "name": "HashCompilerInvocation", "args": { "durationMS": 1.57939994335175, "detail": "UnityEngine.ImageConversionModule_CodeGen.c" } },
{ "pid": 1, "tid": 12, "ts": 1355201.78222656, "dur": 3167.09995269775, "ph": "X", "name": "HashCompilerInvocation", "args": { "durationMS": 3.16709995269775, "detail": "gzclose.c" } },
{ "pid": 1, "tid": 6, "ph": "M", "name": "thread_name", "args": { "name": "" } },
{ "pid": 1, "tid": 6, "ts": 1173191.77246094, "dur": 57231.0028076172, "ph": "X", "name": "HashCompilerInvocation", "args": { "durationMS": 57.2310028076172, "detail": "Il2CppMetadataUsage.c" } },
{ "pid": 1, "tid": 6, "ts": 1230469.48242188, "dur": 8698.8000869751, "ph": "X", "name": "HashCompilerInvocation", "args": { "durationMS": 8.6988000869751, "detail": "Microsoft.MixedReality.Toolkit4.cpp" } },
{ "pid": 1, "tid": 6, "ts": 1239207.51953125, "dur": 8287.79983520508, "ph": "X", "name": "HashCompilerInvocation", "args": { "durationMS": 8.28779983520508, "detail": "Il2CppComCallableWrappers11.cpp" } },
{ "pid": 1, "tid": 6, "ts": 1247539.55078125, "dur": 14422.3003387451, "ph": "X", "name": "HashCompilerInvocation", "args": { "durationMS": 14.4223003387451, "detail": "mscorlib2.cpp" } },
{ "pid": 1, "tid": 6, "ts": 1262002.07519531, "dur": 12516.5004730225, "ph": "X", "name": "HashCompilerInvocation", "args": { "durationMS": 12.5165004730225, "detail": "mscorlib7.cpp" } },
{ "pid": 1, "tid": 6, "ts": 1274556.15234375, "dur": 6933.70008468628, "ph": "X", "name": "HashCompilerInvocation", "args": { "durationMS": 6.93370008468628, "detail": "Generics47.cpp" } },
{ "pid": 1, "tid": 6, "ts": 1281529.296875, "dur": 6348.70004653931, "ph": "X", "name": "HashCompilerInvocation", "args": { "durationMS": 6.34870004653931, "detail": "GenericMethods.cpp" } },
{ "pid": 1, "tid": 6, "ts": 1287921.02050781, "dur": 7454.29992675781, "ph": "X", "name": "HashCompilerInvocation", "args": { "durationMS": 7.45429992675781, "detail": "Generics51.cpp" } },
{ "pid": 1, "tid": 6, "ts": 1295410.88867188, "dur": 7030.09986877441, "ph": "X", "name": "HashCompilerInvocation", "args": { "durationMS": 7.03009986877441, "detail": "Generics37.cpp" } },
{ "pid": 1, "tid": 6, "ts": 1302474.609375, "dur": 8307.39974975586, "ph": "X", "name": "HashCompilerInvocation", "args": { "durationMS": 8.30739974975586, "detail": "Generics11.cpp" } },
{ "pid": 1, "tid": 6, "ts": 1310820.43457031, "dur": 6137.40015029907, "ph": "X", "name": "HashCompilerInvocation", "args": { "durationMS": 6.13740015029907, "detail": "I18N.Rare.cpp" } },
{ "pid": 1, "tid": 6, "ts": 1316995.97167969, "dur": 3707.09991455078, "ph": "X", "name": "HashCompilerInvocation", "args": { "durationMS": 3.70709991455078, "detail": "WindowsRuntimeMetadata.cpp" } },
{ "pid": 1, "tid": 6, "ts": 1320743.77441406, "dur": 3539.70003128052, "ph": "X", "name": "HashCompilerInvocation", "args": { "durationMS": 3.53970003128052, "detail": "UnityEngine.UnityWebRequestModule.cpp" } },
{ "pid": 1, "tid": 6, "ts": 1324327.27050781, "dur": 6146.90017700195, "ph": "X", "name": "HashCompilerInvocation", "args": { "durationMS": 6.14690017700195, "detail": "Unity.TextMeshPro_CodeGen.c" } },
{ "pid": 1, "tid": 6, "ts": 1330526.00097656, "dur": 6830.2001953125, "ph": "X", "name": "HashCompilerInvocation", "args": { "durationMS": 6.8302001953125, "detail": "Microsoft.MixedReality.Toolkit.Services.BoundarySystem.cpp" } },
{ "pid": 1, "tid": 6, "ts": 1337393.92089844, "dur": 1907.50002861023, "ph": "X", "name": "HashCompilerInvocation", "args": { "durationMS": 1.90750002861023, "detail": "Microsoft.MixedReality.Toolkit.Async_CodeGen.c" } },
{ "pid": 1, "tid": 6, "ts": 1340525.51269531, "dur": 1743.70002746582, "ph": "X", "name": "HashCompilerInvocation", "args": { "durationMS": 1.74370002746582, "detail": "UnityEngine.UIModule_CodeGen.c" } },
{ "pid": 1, "tid": 6, "ts": 1342326.29394531, "dur": 1058.30001831055, "ph": "X", "name": "HashCompilerInvocation", "args": { "durationMS": 1.05830001831055, "detail": "UnityEngine.ParticleSystemModule_CodeGen.c" } },
{ "pid": 1, "tid": 6, "ts": 1343432.25097656, "dur": 2269.20008659363, "ph": "X", "name": "HashCompilerInvocation", "args": { "durationMS": 2.26920008659363, "detail": "crc32.c" } },
{ "pid": 1, "tid": 6, "ts": 1345733.88671875, "dur": 2033.49995613098, "ph": "X", "name": "HashCompilerInvocation", "args": { "durationMS": 2.03349995613098, "detail": "System.Configuration_CodeGen.c" } },
{ "pid": 1, "tid": 6, "ts": 1348985.59570313, "dur": 1626.89995765686, "ph": "X", "name": "HashCompilerInvocation", "args": { "durationMS": 1.62689995765686, "detail": "UnityEngine.UnityAnalyticsModule_CodeGen.c" } },
{ "pid": 1, "tid": 6, "ts": 1350648.07128906, "dur": 2670.20010948181, "ph": "X", "name": "HashCompilerInvocation", "args": { "durationMS": 2.67020010948181, "detail": "uncompr.c" } },
{ "pid": 1, "tid": 6, "ts": 1353358.15429688, "dur": 1419.99995708466, "ph": "X", "name": "HashCompilerInvocation", "args": { "durationMS": 1.41999995708466, "detail": "krait_signal_handler.c" } },
{ "pid": 1, "tid": 6, "ts": 1354837.64648438, "dur": 2643.8000202179, "ph": "X", "name": "HashCompilerInvocation", "args": { "durationMS": 2.6438000202179, "detail": "Lump_libil2cpp_gc.cpp" } },
{ "pid": 1, "tid": 6, "ts": 1357556.15234375, "dur": 1178.79998683929, "ph": "X", "name": "HashCompilerInvocation", "args": { "durationMS": 1.17879998683929, "detail": "Lump_libil2cpp_codegen.cpp" } },
{ "pid": 1, "tid": 9, "ph": "M", "name": "thread_name", "args": { "name": "" } },
{ "pid": 1, "tid": 9, "ts": 1173197.50976563, "dur": 31523.6988067627, "ph": "X", "name": "HashCompilerInvocation", "args": { "durationMS": 31.5236988067627, "detail": "Il2CppCompilerCalculateTypeValues1.cpp" } },
{ "pid": 1, "tid": 9, "ts": 1204755.24902344, "dur": 12932.900428772, "ph": "X", "name": "HashCompilerInvocation", "args": { "durationMS": 12.932900428772, "detail": "Microsoft.MixedReality.Toolkit.SDK.cpp" } },
{ "pid": 1, "tid": 9, "ts": 1217738.76953125, "dur": 11686.1000061035, "ph": "X", "name": "HashCompilerInvocation", "args": { "durationMS": 11.6861000061035, "detail": "Generics2.cpp" } },
{ "pid": 1, "tid": 9, "ts": 1229462.15820313, "dur": 8680.39989471436, "ph": "X", "name": "HashCompilerInvocation", "args": { "durationMS": 8.68039989471436, "detail": "mscorlib10.cpp" } },
{ "pid": 1, "tid": 9, "ts": 1238186.15722656, "dur": 7553.40003967285, "ph": "X", "name": "HashCompilerInvocation", "args": { "durationMS": 7.55340003967285, "detail": "mscorlib11.cpp" } },
{ "pid": 1, "tid": 9, "ts": 1245801.02539063, "dur": 8577.79979705811, "ph": "X", "name": "HashCompilerInvocation", "args": { "durationMS": 8.57779979705811, "detail": "mscorlib3.cpp" } },
{ "pid": 1, "tid": 9, "ts": 1254420.04394531, "dur": 10570.6996917725, "ph": "X", "name": "HashCompilerInvocation", "args": { "durationMS": 10.5706996917725, "detail": "Il2CppComCallableWrappers24.cpp" } },
{ "pid": 1, "tid": 9, "ts": 1265024.4140625, "dur": 6431.70022964478, "ph": "X", "name": "HashCompilerInvocation", "args": { "durationMS": 6.43170022964478, "detail": "Unity.TextMeshPro3.cpp" } },
{ "pid": 1, "tid": 9, "ts": 1271492.43164063, "dur": 8838.60015869141, "ph": "X", "name": "HashCompilerInvocation", "args": { "durationMS": 8.83860015869141, "detail": "mscorlib1.cpp" } },
{ "pid": 1, "tid": 9, "ts": 1280368.77441406, "dur": 6505.00011444092, "ph": "X", "name": "HashCompilerInvocation", "args": { "durationMS": 6.50500011444092, "detail": "Il2CppComCallableWrappers5.cpp" } },
{ "pid": 1, "tid": 9, "ts": 1286936.27929688, "dur": 7604.49981689453, "ph": "X", "name": "HashCompilerInvocation", "args": { "durationMS": 7.60449981689453, "detail": "UnresolvedVirtualCallStubs.cpp" } },
{ "pid": 1, "tid": 9, "ts": 1294579.95605469, "dur": 6024.79982376099, "ph": "X", "name": "HashCompilerInvocation", "args": { "durationMS": 6.02479982376099, "detail": "Generics12.cpp" } },
{ "pid": 1, "tid": 9, "ts": 1300641.6015625, "dur": 7364.99977111816, "ph": "X", "name": "HashCompilerInvocation", "args": { "durationMS": 7.36499977111816, "detail": "Il2CppProjectedComCallableWrapperMethods2.cpp" } },
{ "pid": 1, "tid": 9, "ts": 1308042.84667969, "dur": 8209.09976959229, "ph": "X", "name": "HashCompilerInvocation", "args": { "durationMS": 8.20909976959229, "detail": "Generics26.cpp" } },
{ "pid": 1, "tid": 9, "ts": 1316294.18945313, "dur": 4716.49980545044, "ph": "X", "name": "HashCompilerInvocation", "args": { "durationMS": 4.71649980545044, "detail": "UnityEngine.CoreModule2.cpp" } },
{ "pid": 1, "tid": 9, "ts": 1321055.78613281, "dur": 3130.19990921021, "ph": "X", "name": "HashCompilerInvocation", "args": { "durationMS": 3.13019990921021, "detail": "Microsoft.MixedReality.Toolkit.Providers.WindowsVoiceInput.cpp" } },
{ "pid": 1, "tid": 9, "ts": 1324219.36035156, "dur": 3307.19995498657, "ph": "X", "name": "HashCompilerInvocation", "args": { "durationMS": 3.30719995498657, "detail": "DOTweenPro.cpp" } },
{ "pid": 1, "tid": 9, "ts": 1327565.67382813, "dur": 1712.80002593994, "ph": "X", "name": "HashCompilerInvocation", "args": { "durationMS": 1.71280002593994, "detail": "UnityEngine.TextRenderingModule.cpp" } },
{ "pid": 1, "tid": 9, "ts": 1329333.61816406, "dur": 3512.30001449585, "ph": "X", "name": "HashCompilerInvocation", "args": { "durationMS": 3.51230001449585, "detail": "Microsoft.MixedReality.Toolkit.Services.InputSystem_CodeGen.c" } },
{ "pid": 1, "tid": 9, "ts": 1332897.70507813, "dur": 1812.10005283356, "ph": "X", "name": "HashCompilerInvocation", "args": { "durationMS": 1.81210005283356, "detail": "UnityEngine.UnityAnalyticsModule.cpp" } },
{ "pid": 1, "tid": 9, "ts": 1334764.89257813, "dur": 3101.99999809265, "ph": "X", "name": "HashCompilerInvocation", "args": { "durationMS": 3.10199999809265, "detail": "Microsoft.MixedReality.Toolkit.Gltf_CodeGen.c" } },
{ "pid": 1, "tid": 9, "ts": 1337953.73535156, "dur": 2864.59994316101, "ph": "X", "name": "HashCompilerInvocation", "args": { "durationMS": 2.86459994316101, "detail": "Microsoft.MixedReality.Toolkit.Services.DiagnosticsSystem_CodeGen.c" } },
{ "pid": 1, "tid": 9, "ts": 1340854.4921875, "dur": 1775.20000934601, "ph": "X", "name": "HashCompilerInvocation", "args": { "durationMS": 1.77520000934601, "detail": "System.Runtime.WindowsRuntime_CodeGen.c" } },
{ "pid": 1, "tid": 9, "ts": 1342682.86132813, "dur": 2037.30010986328, "ph": "X", "name": "HashCompilerInvocation", "args": { "durationMS": 2.03730010986328, "detail": "Microsoft.MixedReality.Toolkit.Providers.WindowsVoiceInput_CodeGen.c" } },
{ "pid": 1, "tid": 9, "ts": 1344777.22167969, "dur": 1044.99995708466, "ph": "X", "name": "HashCompilerInvocation", "args": { "durationMS": 1.04499995708466, "detail": "inftrees.c" } },
{ "pid": 1, "tid": 9, "ts": 1345860.71777344, "dur": 3120.59998512268, "ph": "X", "name": "HashCompilerInvocation", "args": { "durationMS": 3.12059998512268, "detail": "UnityEngine.VideoModule_CodeGen.c" } },
{ "pid": 1, "tid": 9, "ts": 1349045.53222656, "dur": 2807.80005455017, "ph": "X", "name": "HashCompilerInvocation", "args": { "durationMS": 2.80780005455017, "detail": "adler32.c" } },
{ "pid": 1, "tid": 9, "ts": 1351911.62109375, "dur": 1850.90005397797, "ph": "X", "name": "HashCompilerInvocation", "args": { "durationMS": 1.85090005397797, "detail": "UnityAdsStubs.cpp" } },
{ "pid": 1, "tid": 9, "ts": 1353799.92675781, "dur": 1509.19997692108, "ph": "X", "name": "HashCompilerInvocation", "args": { "durationMS": 1.50919997692108, "detail": "System.Runtime.cpp" } },
{ "pid": 1, "tid": 9, "ts": 1356451.29394531, "dur": 2005.00011444092, "ph": "X", "name": "HashCompilerInvocation", "args": { "durationMS": 2.00500011444092, "detail": "System.Runtime_CodeGen.c" } },
{ "pid": 1, "tid": 7, "ph": "M", "name": "thread_name", "args": { "name": "" } },
{ "pid": 1, "tid": 7, "ts": 1173210.08300781, "dur": 42592.098236084, "ph": "X", "name": "HashCompilerInvocation", "args": { "durationMS": 42.592098236084, "detail": "Il2CppAttributes.cpp" } },
{ "pid": 1, "tid": 7, "ts": 1215854.24804688, "dur": 9996.70028686523, "ph": "X", "name": "HashCompilerInvocation", "args": { "durationMS": 9.99670028686523, "detail": "GenericMethods6.cpp" } },
{ "pid": 1, "tid": 7, "ts": 1225904.78515625, "dur": 10985.1999282837, "ph": "X", "name": "HashCompilerInvocation", "args": { "durationMS": 10.9851999282837, "detail": "Microsoft.MixedReality.Toolkit3.cpp" } },
{ "pid": 1, "tid": 7, "ts": 1236930.17578125, "dur": 7280.49993515015, "ph": "X", "name": "HashCompilerInvocation", "args": { "durationMS": 7.28049993515015, "detail": "Microsoft.MixedReality.Toolkit2.cpp" } },
{ "pid": 1, "tid": 7, "ts": 1244255.12695313, "dur": 8277.70042419434, "ph": "X", "name": "HashCompilerInvocation", "args": { "durationMS": 8.27770042419434, "detail": "Il2CppGenericInstDefinitions.c" } },
{ "pid": 1, "tid": 7, "ts": 1252569.94628906, "dur": 7252.69985198975, "ph": "X", "name": "HashCompilerInvocation", "args": { "durationMS": 7.25269985198975, "detail": "UnityEngine.UI2.cpp" } },
{ "pid": 1, "tid": 7, "ts": 1259862.67089844, "dur": 8206.00032806396, "ph": "X", "name": "HashCompilerInvocation", "args": { "durationMS": 8.20600032806396, "detail": "Generics31.cpp" } },
{ "pid": 1, "tid": 7, "ts": 1268106.4453125, "dur": 7105.89981079102, "ph": "X", "name": "HashCompilerInvocation", "args": { "durationMS": 7.10589981079102, "detail": "Generics20.cpp" } },
{ "pid": 1, "tid": 7, "ts": 1275247.68066406, "dur": 6898.09989929199, "ph": "X", "name": "HashCompilerInvocation", "args": { "durationMS": 6.89809989929199, "detail": "Il2CppComCallableWrappers19.cpp" } },
{ "pid": 1, "tid": 7, "ts": 1282183.95996094, "dur": 6351.6001701355, "ph": "X", "name": "HashCompilerInvocation", "args": { "durationMS": 6.3516001701355, "detail": "Il2CppComCallableWrappers18.cpp" } },
{ "pid": 1, "tid": 7, "ts": 1288571.65527344, "dur": 6999.70006942749, "ph": "X", "name": "HashCompilerInvocation", "args": { "durationMS": 6.99970006942749, "detail": "Il2CppComCallableWrappers8.cpp" } },
{ "pid": 1, "tid": 7, "ts": 1295614.01367188, "dur": 8816.20025634766, "ph": "X", "name": "HashCompilerInvocation", "args": { "durationMS": 8.81620025634766, "detail": "Generics17.cpp" } },
{ "pid": 1, "tid": 7, "ts": 1304476.44042969, "dur": 7168.39981079102, "ph": "X", "name": "HashCompilerInvocation", "args": { "durationMS": 7.16839981079102, "detail": "Generics18.cpp" } },
{ "pid": 1, "tid": 7, "ts": 1311685.05859375, "dur": 6126.69992446899, "ph": "X", "name": "HashCompilerInvocation", "args": { "durationMS": 6.12669992446899, "detail": "Microsoft.MixedReality.Toolkit.SDK_CodeGen.c" } },
{ "pid": 1, "tid": 7, "ts": 1317848.87695313, "dur": 4442.90018081665, "ph": "X", "name": "HashCompilerInvocation", "args": { "durationMS": 4.44290018081665, "detail": "I18N.cpp" } },
{ "pid": 1, "tid": 7, "ts": 1322328.125, "dur": 3460.79993247986, "ph": "X", "name": "HashCompilerInvocation", "args": { "durationMS": 3.46079993247986, "detail": "UnityEngine.UI_CodeGen.c" } },
{ "pid": 1, "tid": 7, "ts": 1325893.18847656, "dur": 2510.99991798401, "ph": "X", "name": "HashCompilerInvocation", "args": { "durationMS": 2.51099991798401, "detail": "Microsoft.MixedReality.Toolkit.Services.InputSystem1.cpp" } },
{ "pid": 1, "tid": 7, "ts": 1328439.20898438, "dur": 1726.09996795654, "ph": "X", "name": "HashCompilerInvocation", "args": { "durationMS": 1.72609996795654, "detail": "DOTween_CodeGen.c" } },
{ "pid": 1, "tid": 7, "ts": 1330207.51953125, "dur": 3132.20000267029, "ph": "X", "name": "HashCompilerInvocation", "args": { "durationMS": 3.13220000267029, "detail": "UnityEngine.VRModule_CodeGen.c" } },
{ "pid": 1, "tid": 7, "ts": 1333373.16894531, "dur": 1657.50002861023, "ph": "X", "name": "HashCompilerInvocation", "args": { "durationMS": 1.65750002861023, "detail": "Microsoft.MixedReality.Toolkit.Providers.WindowsMixedReality_CodeGen.c" } },
{ "pid": 1, "tid": 7, "ts": 1335079.83398438, "dur": 2703.79996299744, "ph": "X", "name": "HashCompilerInvocation", "args": { "durationMS": 2.70379996299744, "detail": "trees.c" } },
{ "pid": 1, "tid": 7, "ts": 1337831.66503906, "dur": 2699.10001754761, "ph": "X", "name": "HashCompilerInvocation", "args": { "durationMS": 2.69910001754761, "detail": "UnityEngine.UnityWebRequestModule_CodeGen.c" } },
{ "pid": 1, "tid": 7, "ts": 1340572.50976563, "dur": 2463.29998970032, "ph": "X", "name": "HashCompilerInvocation", "args": { "durationMS": 2.46329998970032, "detail": "Lump_libil2cpp_os.cpp" } },
{ "pid": 1, "tid": 7, "ts": 1343068.23730469, "dur": 2616.30010604858, "ph": "X", "name": "HashCompilerInvocation", "args": { "durationMS": 2.61630010604858, "detail": "Microsoft.MixedReality.Toolkit.Providers.WindowsMixedReality.Shared_CodeGen.c" } },
{ "pid": 1, "tid": 7, "ts": 1345784.54589844, "dur": 2002.89988517761, "ph": "X", "name": "HashCompilerInvocation", "args": { "durationMS": 2.00289988517761, "detail": "UnityEngine.ImageConversionModule.cpp" } },
{ "pid": 1, "tid": 7, "ts": 1349012.08496094, "dur": 1758.29994678497, "ph": "X", "name": "HashCompilerInvocation", "args": { "durationMS": 1.75829994678497, "detail": "UnityEngine.GridModule.cpp" } },
{ "pid": 1, "tid": 7, "ts": 1350819.3359375, "dur": 2619.69995498657, "ph": "X", "name": "HashCompilerInvocation", "args": { "durationMS": 2.61969995498657, "detail": "compress.c" } },
{ "pid": 1, "tid": 7, "ts": 1353470.09277344, "dur": 1349.20001029968, "ph": "X", "name": "HashCompilerInvocation", "args": { "durationMS": 1.34920001029968, "detail": "UnityEngine.AssetBundleModule_CodeGen.c" } },
{ "pid": 1, "tid": 7, "ts": 1354854.00390625, "dur": 2834.70010757446, "ph": "X", "name": "HashCompilerInvocation", "args": { "durationMS": 2.83470010757446, "detail": "UnityEngine.GridModule_CodeGen.c" } },
{ "pid": 1, "tid": 5, "ph": "M", "name": "thread_name", "args": { "name": "" } },
{ "pid": 1, "tid": 5, "ts": 1173212.03613281, "dur": 42799.9000549316, "ph": "X", "name": "HashCompilerInvocation", "args": { "durationMS": 42.7999000549316, "detail": "Il2CppGenericMethodPointerTable.cpp" } },
{ "pid": 1, "tid": 5, "ts": 1216051.02539063, "dur": 8942.09957122803, "ph": "X", "name": "HashCompilerInvocation", "args": { "durationMS": 8.94209957122803, "detail": "mscorlib6.cpp" } },
{ "pid": 1, "tid": 5, "ts": 1225030.15136719, "dur": 9764.39952850342, "ph": "X", "name": "HashCompilerInvocation", "args": { "durationMS": 9.76439952850342, "detail": "Generics39.cpp" } },
{ "pid": 1, "tid": 5, "ts": 1234846.6796875, "dur": 7521.69990539551, "ph": "X", "name": "HashCompilerInvocation", "args": { "durationMS": 7.52169990539551, "detail": "Unity.TextMeshPro2.cpp" } },
{ "pid": 1, "tid": 5, "ts": 1242411.62109375, "dur": 8624.19986724854, "ph": "X", "name": "HashCompilerInvocation", "args": { "durationMS": 8.62419986724854, "detail": "mscorlib9.cpp" } },
{ "pid": 1, "tid": 5, "ts": 1251077.02636719, "dur": 7705.2001953125, "ph": "X", "name": "HashCompilerInvocation", "args": { "durationMS": 7.7052001953125, "detail": "UnityEngine.CoreModule.cpp" } },
{ "pid": 1, "tid": 5, "ts": 1258823.12011719, "dur": 8644.90032196045, "ph": "X", "name": "HashCompilerInvocation", "args": { "durationMS": 8.64490032196045, "detail": "Generics40.cpp" } },
{ "pid": 1, "tid": 5, "ts": 1267505.00488281, "dur": 11970.8003997803, "ph": "X", "name": "HashCompilerInvocation", "args": { "durationMS": 11.9708003997803, "detail": "Il2CppComCallableWrappers20.cpp" } },
{ "pid": 1, "tid": 5, "ts": 1279521.85058594, "dur": 7174.60012435913, "ph": "X", "name": "HashCompilerInvocation", "args": { "durationMS": 7.17460012435913, "detail": "Il2CppComCallableWrappers27.cpp" } },
{ "pid": 1, "tid": 5, "ts": 1286737.91503906, "dur": 7329.50019836426, "ph": "X", "name": "HashCompilerInvocation", "args": { "durationMS": 7.32950019836426, "detail": "Generics42.cpp" } },
{ "pid": 1, "tid": 5, "ts": 1294105.95703125, "dur": 6431.00023269653, "ph": "X", "name": "HashCompilerInvocation", "args": { "durationMS": 6.43100023269653, "detail": "Generics34.cpp" } },
{ "pid": 1, "tid": 5, "ts": 1300574.82910156, "dur": 6719.90013122559, "ph": "X", "name": "HashCompilerInvocation", "args": { "durationMS": 6.71990013122559, "detail": "Microsoft.MixedReality.Toolkit.Providers.WindowsMixedReality.cpp" } },
{ "pid": 1, "tid": 5, "ts": 1307333.0078125, "dur": 6461.50016784668, "ph": "X", "name": "HashCompilerInvocation", "args": { "durationMS": 6.46150016784668, "detail": "Generics16.cpp" } },
{ "pid": 1, "tid": 5, "ts": 1313837.40234375, "dur": 4253.79991531372, "ph": "X", "name": "HashCompilerInvocation", "args": { "durationMS": 4.25379991531372, "detail": "Microsoft.MixedReality.Toolkit.Services.SceneSystem.cpp" } },
{ "pid": 1, "tid": 5, "ts": 1318125, "dur": 4168.30015182495, "ph": "X", "name": "HashCompilerInvocation", "args": { "durationMS": 4.16830015182495, "detail": "UnityEngine.CoreModule_CodeGen.c" } },
{ "pid": 1, "tid": 5, "ts": 1322331.17675781, "dur": 3384.99999046326, "ph": "X", "name": "HashCompilerInvocation", "args": { "durationMS": 3.38499999046326, "detail": "UnityEngine.XRModule.cpp" } },
{ "pid": 1, "tid": 5, "ts": 1325749.26757813, "dur": 2491.60003662109, "ph": "X", "name": "HashCompilerInvocation", "args": { "durationMS": 2.49160003662109, "detail": "UnityEngine.AnimationModule.cpp" } },
{ "pid": 1, "tid": 5, "ts": 1328275.26855469, "dur": 2174.70002174377, "ph": "X", "name": "HashCompilerInvocation", "args": { "durationMS": 2.17470002174377, "detail": "Microsoft.MixedReality.Toolkit.Services.TeleportSystem.cpp" } },
{ "pid": 1, "tid": 5, "ts": 1330510.13183594, "dur": 3160.20011901855, "ph": "X", "name": "HashCompilerInvocation", "args": { "durationMS": 3.16020011901855, "detail": "UnityEngine.UIElementsModule.cpp" } },
{ "pid": 1, "tid": 5, "ts": 1333963.01269531, "dur": 3262.90011405945, "ph": "X", "name": "HashCompilerInvocation", "args": { "durationMS": 3.26290011405945, "detail": "UnityEngine.InputModule.cpp" } },
{ "pid": 1, "tid": 5, "ts": 1337262.6953125, "dur": 1559.10003185272, "ph": "X", "name": "HashCompilerInvocation", "args": { "durationMS": 1.55910003185272, "detail": "Microsoft.MixedReality.Toolkit.Services.InputAnimation_CodeGen.c" } },
{ "pid": 1, "tid": 5, "ts": 1338858.15429688, "dur": 2811.70010566711, "ph": "X", "name": "HashCompilerInvocation", "args": { "durationMS": 2.81170010566711, "detail": "UnityEngine.XRModule_CodeGen.c" } },
{ "pid": 1, "tid": 5, "ts": 1341704.22363281, "dur": 1314.49997425079, "ph": "X", "name": "HashCompilerInvocation", "args": { "durationMS": 1.31449997425079, "detail": "UnityEngine.DirectorModule.cpp" } },
{ "pid": 1, "tid": 5, "ts": 1343049.31640625, "dur": 2566.60008430481, "ph": "X", "name": "HashCompilerInvocation", "args": { "durationMS": 2.56660008430481, "detail": "UnityEngine.TextRenderingModule_CodeGen.c" } },
{ "pid": 1, "tid": 5, "ts": 1345650.02441406, "dur": 4237.99991607666, "ph": "X", "name": "HashCompilerInvocation", "args": { "durationMS": 4.23799991607666, "detail": "Microsoft.MixedReality.Toolkit.Services.SpatialAwarenessSystem_CodeGen.c" } },
{ "pid": 1, "tid": 5, "ts": 1349987.18261719, "dur": 1253.99994850159, "ph": "X", "name": "HashCompilerInvocation", "args": { "durationMS": 1.25399994850159, "detail": "Mono.Security_CodeGen.c" } },
{ "pid": 1, "tid": 5, "ts": 1351896.11816406, "dur": 1824.30005073547, "ph": "X", "name": "HashCompilerInvocation", "args": { "durationMS": 1.82430005073547, "detail": "Lump_libil2cpp_utils.cpp" } },
{ "pid": 1, "tid": 5, "ts": 1353760.62011719, "dur": 1539.19994831085, "ph": "X", "name": "HashCompilerInvocation", "args": { "durationMS": 1.53919994831085, "detail": "System.ObjectModel.cpp" } },
{ "pid": 1, "tid": 5, "ts": 1355333.984375, "dur": 5108.39986801147, "ph": "X", "name": "HashCompilerInvocation", "args": { "durationMS": 5.10839986801147, "detail": "System.ObjectModel_CodeGen.c" } },
{ "pid": 1, "tid": 8, "ph": "M", "name": "thread_name", "args": { "name": "" } },
{ "pid": 1, "tid": 8, "ts": 1173841.796875, "dur": 37245.2011108398, "ph": "X", "name": "HashCompilerInvocation", "args": { "durationMS": 37.2452011108398, "detail": "Il2CppGenericMethodDefinitions.c" } },
{ "pid": 1, "tid": 8, "ts": 1211141.96777344, "dur": 10115.5004501343, "ph": "X", "name": "HashCompilerInvocation", "args": { "durationMS": 10.1155004501343, "detail": "mscorlib_CodeGen.c" } },
{ "pid": 1, "tid": 8, "ts": 1221298.95019531, "dur": 8550.70018768311, "ph": "X", "name": "HashCompilerInvocation", "args": { "durationMS": 8.55070018768311, "detail": "Microsoft.MixedReality.Toolkit.SDK2.cpp" } },
{ "pid": 1, "tid": 8, "ts": 1229899.78027344, "dur": 9417.3002243042, "ph": "X", "name": "HashCompilerInvocation", "args": { "durationMS": 9.4173002243042, "detail": "UnityEngine.UI.cpp" } },
{ "pid": 1, "tid": 8, "ts": 1239358.27636719, "dur": 8446.49982452393, "ph": "X", "name": "HashCompilerInvocation", "args": { "durationMS": 8.44649982452393, "detail": "GenericMethods5.cpp" } },
{ "pid": 1, "tid": 8, "ts": 1247844.60449219, "dur": 7558.89987945557, "ph": "X", "name": "HashCompilerInvocation", "args": { "durationMS": 7.55889987945557, "detail": "Il2CppComCallableWrappers26.cpp" } },
{ "pid": 1, "tid": 8, "ts": 1255442.87109375, "dur": 9884.59968566895, "ph": "X", "name": "HashCompilerInvocation", "args": { "durationMS": 9.88459968566895, "detail": "Il2CppComCallableWrappers16.cpp" } },
{ "pid": 1, "tid": 8, "ts": 1265365.11230469, "dur": 9016.09992980957, "ph": "X", "name": "HashCompilerInvocation", "args": { "durationMS": 9.01609992980957, "detail": "mscorlib13.cpp" } },
{ "pid": 1, "tid": 8, "ts": 1274420.41015625, "dur": 6829.80012893677, "ph": "X", "name": "HashCompilerInvocation", "args": { "durationMS": 6.82980012893677, "detail": "Il2CppComCallableWrappers28.cpp" } },
{ "pid": 1, "tid": 8, "ts": 1281285.03417969, "dur": 6381.8998336792, "ph": "X", "name": "HashCompilerInvocation", "args": { "durationMS": 6.3818998336792, "detail": "Il2CppComCallableWrappers4.cpp" } },
{ "pid": 1, "tid": 8, "ts": 1287703.00292969, "dur": 6858.30020904541, "ph": "X", "name": "HashCompilerInvocation", "args": { "durationMS": 6.85830020904541, "detail": "Generics44.cpp" } },
{ "pid": 1, "tid": 8, "ts": 1294600.34179688, "dur": 6224.50017929077, "ph": "X", "name": "HashCompilerInvocation", "args": { "durationMS": 6.22450017929077, "detail": "Il2CppComCallableWrappers2.cpp" } },
{ "pid": 1, "tid": 8, "ts": 1300861.69433594, "dur": 6325.90007781982, "ph": "X", "name": "HashCompilerInvocation", "args": { "durationMS": 6.32590007781982, "detail": "Generics28.cpp" } },
{ "pid": 1, "tid": 8, "ts": 1307243.53027344, "dur": 6555.79996109009, "ph": "X", "name": "HashCompilerInvocation", "args": { "durationMS": 6.55579996109009, "detail": "Generics22.cpp" } },
{ "pid": 1, "tid": 8, "ts": 1313845.09277344, "dur": 8748.70014190674, "ph": "X", "name": "HashCompilerInvocation", "args": { "durationMS": 8.74870014190674, "detail": "Il2CppGenericComDefinitions.cpp" } },
{ "pid": 1, "tid": 8, "ts": 1322632.69042969, "dur": 3154.90007400513, "ph": "X", "name": "HashCompilerInvocation", "args": { "durationMS": 3.15490007400513, "detail": "GenericMethods9.cpp" } },
{ "pid": 1, "tid": 8, "ts": 1325827.1484375, "dur": 2409.49988365173, "ph": "X", "name": "HashCompilerInvocation", "args": { "durationMS": 2.40949988365173, "detail": "UnityEngine.TerrainModule.cpp" } },
{ "pid": 1, "tid": 8, "ts": 1328268.43261719, "dur": 1902.1999835968, "ph": "X", "name": "HashCompilerInvocation", "args": { "durationMS": 1.9021999835968, "detail": "System.Runtime.WindowsRuntime.cpp" } },
{ "pid": 1, "tid": 8, "ts": 1330209.71679688, "dur": 3150.30002593994, "ph": "X", "name": "HashCompilerInvocation", "args": { "durationMS": 3.15030002593994, "detail": "WindowsRuntimeMetadata_CodeGen.c" } },
{ "pid": 1, "tid": 8, "ts": 1333387.57324219, "dur": 2305.79996109009, "ph": "X", "name": "HashCompilerInvocation", "args": { "durationMS": 2.30579996109009, "detail": "I18N.Rare_CodeGen.c" } },
{ "pid": 1, "tid": 8, "ts": 1338949.21875, "dur": 2715.10004997253, "ph": "X", "name": "HashCompilerInvocation", "args": { "durationMS": 2.71510004997253, "detail": "Il2CppProjectedComCallableWrapperMethods5.cpp" } },
{ "pid": 1, "tid": 8, "ts": 1341708.12988281, "dur": 1439.80002403259, "ph": "X", "name": "HashCompilerInvocation", "args": { "durationMS": 1.43980002403259, "detail": "gzread.c" } },
{ "pid": 1, "tid": 8, "ts": 1343202.27050781, "dur": 2571.39992713928, "ph": "X", "name": "HashCompilerInvocation", "args": { "durationMS": 2.57139992713928, "detail": "UnityEngine.Physics2DModule_CodeGen.c" } },
{ "pid": 1, "tid": 8, "ts": 1345900.390625, "dur": 1887.09998130798, "ph": "X", "name": "HashCompilerInvocation", "args": { "durationMS": 1.88709998130798, "detail": "UnityEngine.TilemapModule_CodeGen.c" } },
{ "pid": 1, "tid": 8, "ts": 1349012.08496094, "dur": 2841.20011329651, "ph": "X", "name": "HashCompilerInvocation", "args": { "durationMS": 2.84120011329651, "detail": "System.Xml_CodeGen.c" } },
{ "pid": 1, "tid": 8, "ts": 1351911.25488281, "dur": 1891.1999464035, "ph": "X", "name": "HashCompilerInvocation", "args": { "durationMS": 1.8911999464035, "detail": "UnityEngine.AIModule_CodeGen.c" } },
{ "pid": 1, "tid": 8, "ts": 1353839.11132813, "dur": 1489.50004577637, "ph": "X", "name": "HashCompilerInvocation", "args": { "durationMS": 1.48950004577637, "detail": "UnityEngine.cpp" } },
{ "pid": 1, "tid": 8, "ts": 1356472.41210938, "dur": 2027.49991416931, "ph": "X", "name": "HashCompilerInvocation", "args": { "durationMS": 2.02749991416931, "detail": "UnityEngine_CodeGen.c" } },
{ "pid": 1, "tid": 10, "ph": "M", "name": "thread_name", "args": { "name": "" } },
{ "pid": 1, "tid": 10, "ts": 1173901.3671875, "dur": 30976.4995574951, "ph": "X", "name": "HashCompilerInvocation", "args": { "durationMS": 30.9764995574951, "detail": "Il2CppInvokerTable.cpp" } },
{ "pid": 1, "tid": 10, "ts": 1204925.29296875, "dur": 14548.4991073608, "ph": "X", "name": "HashCompilerInvocation", "args": { "durationMS": 14.5484991073608, "detail": "Microsoft.MixedReality.Toolkit.SDK3.cpp" } },
{ "pid": 1, "tid": 10, "ts": 1219513.91601563, "dur": 9664.79969024658, "ph": "X", "name": "HashCompilerInvocation", "args": { "durationMS": 9.66479969024658, "detail": "Microsoft.MixedReality.Toolkit1.cpp" } },
{ "pid": 1, "tid": 10, "ts": 1229225.21972656, "dur": 9107.00035095215, "ph": "X", "name": "HashCompilerInvocation", "args": { "durationMS": 9.10700035095215, "detail": "Generics7.cpp" } },
{ "pid": 1, "tid": 10, "ts": 1238368.04199219, "dur": 9302.90031433105, "ph": "X", "name": "HashCompilerInvocation", "args": { "durationMS": 9.30290031433105, "detail": "mscorlib15.cpp" } },
{ "pid": 1, "tid": 10, "ts": 1247710.81542969, "dur": 6614.09997940063, "ph": "X", "name": "HashCompilerInvocation", "args": { "durationMS": 6.61409997940063, "detail": "UnityEngine.CoreModule1.cpp" } },
{ "pid": 1, "tid": 10, "ts": 1254364.86816406, "dur": 11956.7003250122, "ph": "X", "name": "HashCompilerInvocation", "args": { "durationMS": 11.9567003250122, "detail": "Generics25.cpp" } },
{ "pid": 1, "tid": 10, "ts": 1266383.54492188, "dur": 6390.79999923706, "ph": "X", "name": "HashCompilerInvocation", "args": { "durationMS": 6.39079999923706, "detail": "System.cpp" } },
{ "pid": 1, "tid": 10, "ts": 1272811.5234375, "dur": 8165.69995880127, "ph": "X", "name": "HashCompilerInvocation", "args": { "durationMS": 8.16569995880127, "detail": "Il2CppComCallableWrappers15.cpp" } },
{ "pid": 1, "tid": 10, "ts": 1281017.70019531, "dur": 10396.6999053955, "ph": "X", "name": "HashCompilerInvocation", "args": { "durationMS": 10.3966999053955, "detail": "Generics23.cpp" } },
{ "pid": 1, "tid": 10, "ts": 1291455.68847656, "dur": 13192.0003890991, "ph": "X", "name": "HashCompilerInvocation", "args": { "durationMS": 13.1920003890991, "detail": "Generics50.cpp" } },
{ "pid": 1, "tid": 10, "ts": 1304694.45800781, "dur": 7433.00008773804, "ph": "X", "name": "HashCompilerInvocation", "args": { "durationMS": 7.43300008773804, "detail": "Il2CppProjectedComCallableWrapperMethods1.cpp" } },
{ "pid": 1, "tid": 10, "ts": 1312163.69628906, "dur": 5492.00010299683, "ph": "X", "name": "HashCompilerInvocation", "args": { "durationMS": 5.49200010299683, "detail": "mscorlib16.cpp" } },
{ "pid": 1, "tid": 10, "ts": 1317700.56152344, "dur": 5012.10021972656, "ph": "X", "name": "HashCompilerInvocation", "args": { "durationMS": 5.01210021972656, "detail": "I18N.CJK.cpp" } },
{ "pid": 1, "tid": 10, "ts": 1322751.83105469, "dur": 4303.59983444214, "ph": "X", "name": "HashCompilerInvocation", "args": { "durationMS": 4.30359983444214, "detail": "Generics52.cpp" } },
{ "pid": 1, "tid": 10, "ts": 1327092.65136719, "dur": 1618.00003051758, "ph": "X", "name": "HashCompilerInvocation", "args": { "durationMS": 1.61800003051758, "detail": "UnityEngine.UIModule.cpp" } },
{ "pid": 1, "tid": 10, "ts": 1328754.27246094, "dur": 3774.49989318848, "ph": "X", "name": "HashCompilerInvocation", "args": { "durationMS": 3.77449989318848, "detail": "Microsoft.MixedReality.Toolkit.Services.SpatialAwarenessSystem.cpp" } },
{ "pid": 1, "tid": 10, "ts": 1332577.63671875, "dur": 1391.4999961853, "ph": "X", "name": "HashCompilerInvocation", "args": { "durationMS": 1.3914999961853, "detail": "System.Configuration.cpp" } },
{ "pid": 1, "tid": 10, "ts": 1334026.73339844, "dur": 3381.29997253418, "ph": "X", "name": "HashCompilerInvocation", "args": { "durationMS": 3.38129997253418, "detail": "System.Xml.cpp" } },
{ "pid": 1, "tid": 10, "ts": 1337451.04980469, "dur": 1734.20000076294, "ph": "X", "name": "HashCompilerInvocation", "args": { "durationMS": 1.73420000076294, "detail": "il2cpp-api.cpp" } },
{ "pid": 1, "tid": 10, "ts": 1341952.51464844, "dur": 1276.00002288818, "ph": "X", "name": "HashCompilerInvocation", "args": { "durationMS": 1.27600002288818, "detail": "UnityEngine.AnimationModule_CodeGen.c" } },
{ "pid": 1, "tid": 10, "ts": 1343268.79882813, "dur": 6619.10009384155, "ph": "X", "name": "HashCompilerInvocation", "args": { "durationMS": 6.61910009384155, "detail": "UnityEngine.TerrainModule_CodeGen.c" } },
{ "pid": 1, "tid": 10, "ts": 1349948.60839844, "dur": 3624.00007247925, "ph": "X", "name": "HashCompilerInvocation", "args": { "durationMS": 3.62400007247925, "detail": "UnityEngine.TerrainPhysicsModule.cpp" } },
{ "pid": 1, "tid": 10, "ts": 1353617.91992188, "dur": 1614.09997940063, "ph": "X", "name": "HashCompilerInvocation", "args": { "durationMS": 1.61409997940063, "detail": "Il2CppMetadataRegistration.c" } },
{ "pid": 1, "tid": 10, "ts": 1355263.79394531, "dur": 3093.89996528625, "ph": "X", "name": "HashCompilerInvocation", "args": { "durationMS": 3.09389996528625, "detail": "System.Runtime.InteropServices.WindowsRuntime_CodeGen.c" } },
{ "pid": 1, "tid": 3, "ph": "M", "name": "thread_name", "args": { "name": "" } },
{ "pid": 1, "tid": 3, "ts": 1173954.46777344, "dur": 95382.0037841797, "ph": "X", "name": "HashCompilerInvocation", "args": { "durationMS": 95.3820037841797, "detail": "Il2CppTypeDefinitions.c" } },
{ "pid": 1, "tid": 3, "ts": 1269374.26757813, "dur": 7252.60019302368, "ph": "X", "name": "HashCompilerInvocation", "args": { "durationMS": 7.25260019302368, "detail": "Generics.cpp" } },
{ "pid": 1, "tid": 3, "ts": 1276666.25976563, "dur": 6884.30023193359, "ph": "X", "name": "HashCompilerInvocation", "args": { "durationMS": 6.88430023193359, "detail": "Generics30.cpp" } },
{ "pid": 1, "tid": 3, "ts": 1283588.25683594, "dur": 8610.60047149658, "ph": "X", "name": "HashCompilerInvocation", "args": { "durationMS": 8.61060047149658, "detail": "Generics29.cpp" } },
{ "pid": 1, "tid": 3, "ts": 1292238.76953125, "dur": 5595.49999237061, "ph": "X", "name": "HashCompilerInvocation", "args": { "durationMS": 5.59549999237061, "detail": "Generics32.cpp" } },
{ "pid": 1, "tid": 3, "ts": 1297875.48828125, "dur": 7233.69979858398, "ph": "X", "name": "HashCompilerInvocation", "args": { "durationMS": 7.23369979858398, "detail": "Generics43.cpp" } },
{ "pid": 1, "tid": 3, "ts": 1305148.92578125, "dur": 6498.60000610352, "ph": "X", "name": "HashCompilerInvocation", "args": { "durationMS": 6.49860000610352, "detail": "Generics6.cpp" } },
{ "pid": 1, "tid": 3, "ts": 1311682.6171875, "dur": 6372.39980697632, "ph": "X", "name": "HashCompilerInvocation", "args": { "durationMS": 6.37239980697632, "detail": "UnityEngine.VRModule.cpp" } },
{ "pid": 1, "tid": 3, "ts": 1318095.94726563, "dur": 7120.29981613159, "ph": "X", "name": "HashCompilerInvocation", "args": { "durationMS": 7.12029981613159, "detail": "Microsoft.MixedReality.Toolkit.Services.InputAnimation.cpp" } },
{ "pid": 1, "tid": 3, "ts": 1325254.51660156, "dur": 2755.50007820129, "ph": "X", "name": "HashCompilerInvocation", "args": { "durationMS": 2.75550007820129, "detail": "DOTween46.cpp" } },
{ "pid": 1, "tid": 3, "ts": 1328042.23632813, "dur": 1683.69996547699, "ph": "X", "name": "HashCompilerInvocation", "args": { "durationMS": 1.68369996547699, "detail": "System.Numerics.cpp" } },
{ "pid": 1, "tid": 3, "ts": 1329758.30078125, "dur": 3342.99993515015, "ph": "X", "name": "HashCompilerInvocation", "args": { "durationMS": 3.34299993515015, "detail": "Microsoft.MixedReality.Toolkit.Services.CameraSystem.cpp" } },
{ "pid": 1, "tid": 3, "ts": 1333138.671875, "dur": 1430.60004711151, "ph": "X", "name": "HashCompilerInvocation", "args": { "durationMS": 1.43060004711151, "detail": "Assembly-CSharp_CodeGen.c" } },
{ "pid": 1, "tid": 3, "ts": 1334623.41308594, "dur": 3233.79993438721, "ph": "X", "name": "HashCompilerInvocation", "args": { "durationMS": 3.23379993438721, "detail": "Microsoft.MixedReality.Toolkit.Services.SceneSystem_CodeGen.c" } },
{ "pid": 1, "tid": 3, "ts": 1337900.390625, "dur": 2825.09994506836, "ph": "X", "name": "HashCompilerInvocation", "args": { "durationMS": 2.82509994506836, "detail": "System.Core.cpp" } },
{ "pid": 1, "tid": 3, "ts": 1340777.09960938, "dur": 2305.79996109009, "ph": "X", "name": "HashCompilerInvocation", "args": { "durationMS": 2.30579996109009, "detail": "Lump_libil2cpp_icalls.cpp" } },
{ "pid": 1, "tid": 3, "ts": 1343127.31933594, "dur": 2368.40009689331, "ph": "X", "name": "HashCompilerInvocation", "args": { "durationMS": 2.36840009689331, "detail": "gzlib.c" } },
{ "pid": 1, "tid": 3, "ts": 1345534.79003906, "dur": 2035.00008583069, "ph": "X", "name": "HashCompilerInvocation", "args": { "durationMS": 2.03500008583069, "detail": "Il2CppCodeRegistration.cpp" } },
{ "pid": 1, "tid": 3, "ts": 1347598.14453125, "dur": 2624.50003623962, "ph": "X", "name": "HashCompilerInvocation", "args": { "durationMS": 2.62450003623962, "detail": "Lump_libil2cpp_vm.cpp" } },
{ "pid": 1, "tid": 3, "ts": 1350264.03808594, "dur": 1587.1000289917, "ph": "X", "name": "HashCompilerInvocation", "args": { "durationMS": 1.5871000289917, "detail": "UnityEngine.InputModule_CodeGen.c" } },
{ "pid": 1, "tid": 3, "ts": 1351885.86425781, "dur": 1899.99997615814, "ph": "X", "name": "HashCompilerInvocation", "args": { "durationMS": 1.89999997615814, "detail": "UnityEngine.JSONSerializeModule_CodeGen.c" } },
{ "pid": 1, "tid": 3, "ts": 1353828.36914063, "dur": 1406.49998188019, "ph": "X", "name": "HashCompilerInvocation", "args": { "durationMS": 1.40649998188019, "detail": "System.Runtime.InteropServices.WindowsRuntime.cpp" } },
{ "pid": 1, "tid": 3, "ts": 1355267.45605469, "dur": 4300.89998245239, "ph": "X", "name": "HashCompilerInvocation", "args": { "durationMS": 4.30089998245239, "detail": "UnityEngine.TerrainPhysicsModule_CodeGen.c" } },
{ "pid": 1, "tid": 4, "ph": "M", "name": "thread_name", "args": { "name": "" } },
{ "pid": 1, "tid": 4, "ts": 1173979.98046875, "dur": 31798.0003356934, "ph": "X", "name": "HashCompilerInvocation", "args": { "durationMS": 31.7980003356934, "detail": "Il2CppGenericMethodTable.c" } },
{ "pid": 1, "tid": 4, "ts": 1205816.28417969, "dur": 13366.2004470825, "ph": "X", "name": "HashCompilerInvocation", "args": { "durationMS": 13.3662004470825, "detail": "Microsoft.MixedReality.Toolkit.SDK5.cpp" } },
{ "pid": 1, "tid": 4, "ts": 1219224.12109375, "dur": 8397.50003814697, "ph": "X", "name": "HashCompilerInvocation", "args": { "durationMS": 8.39750003814697, "detail": "Microsoft.MixedReality.Toolkit.SDK1.cpp" } },
{ "pid": 1, "tid": 4, "ts": 1227656.98242188, "dur": 11993.5998916626, "ph": "X", "name": "HashCompilerInvocation", "args": { "durationMS": 11.9935998916626, "detail": "GenericMethods1.cpp" } },
{ "pid": 1, "tid": 4, "ts": 1239691.28417969, "dur": 9500.20027160645, "ph": "X", "name": "HashCompilerInvocation", "args": { "durationMS": 9.50020027160645, "detail": "mscorlib14.cpp" } },
{ "pid": 1, "tid": 4, "ts": 1249235.10742188, "dur": 8216.89987182617, "ph": "X", "name": "HashCompilerInvocation", "args": { "durationMS": 8.21689987182617, "detail": "System1.cpp" } },
{ "pid": 1, "tid": 4, "ts": 1257509.15527344, "dur": 7488.29984664917, "ph": "X", "name": "HashCompilerInvocation", "args": { "durationMS": 7.48829984664917, "detail": "Il2CppComCallableWrappers9.cpp" } },
{ "pid": 1, "tid": 4, "ts": 1265024.53613281, "dur": 6438.39979171753, "ph": "X", "name": "HashCompilerInvocation", "args": { "durationMS": 6.43839979171753, "detail": "mscorlib12.cpp" } },
{ "pid": 1, "tid": 4, "ts": 1271501.22070313, "dur": 8399.29962158203, "ph": "X", "name": "HashCompilerInvocation", "args": { "durationMS": 8.39929962158203, "detail": "DOTween.cpp" } },
{ "pid": 1, "tid": 4, "ts": 1279938.11035156, "dur": 7017.60005950928, "ph": "X", "name": "HashCompilerInvocation", "args": { "durationMS": 7.01760005950928, "detail": "Generics48.cpp" } },
{ "pid": 1, "tid": 4, "ts": 1287038.81835938, "dur": 6546.50020599365, "ph": "X", "name": "HashCompilerInvocation", "args": { "durationMS": 6.54650020599365, "detail": "Generics33.cpp" } },
{ "pid": 1, "tid": 4, "ts": 1293624.87792969, "dur": 6021.69990539551, "ph": "X", "name": "HashCompilerInvocation", "args": { "durationMS": 6.02169990539551, "detail": "Generics36.cpp" } },
{ "pid": 1, "tid": 4, "ts": 1299691.16210938, "dur": 6495.90015411377, "ph": "X", "name": "HashCompilerInvocation", "args": { "durationMS": 6.49590015411377, "detail": "Microsoft.MixedReality.Toolkit.Gltf.cpp" } },
{ "pid": 1, "tid": 4, "ts": 1306232.05566406, "dur": 6106.69994354248, "ph": "X", "name": "HashCompilerInvocation", "args": { "durationMS": 6.10669994354248, "detail": "Il2CppProjectedComCallableWrapperMethods.cpp" } },
{ "pid": 1, "tid": 4, "ts": 1312377.56347656, "dur": 5724.40004348755, "ph": "X", "name": "HashCompilerInvocation", "args": { "durationMS": 5.72440004348755, "detail": "Microsoft.MixedReality.Toolkit_CodeGen.c" } },
{ "pid": 1, "tid": 4, "ts": 1318156.12792969, "dur": 4138.50021362305, "ph": "X", "name": "HashCompilerInvocation", "args": { "durationMS": 4.13850021362305, "detail": "Microsoft.MixedReality.Toolkit.Services.DiagnosticsSystem.cpp" } },
{ "pid": 1, "tid": 4, "ts": 1322339.72167969, "dur": 3413.80000114441, "ph": "X", "name": "HashCompilerInvocation", "args": { "durationMS": 3.41380000114441, "detail": "Microsoft.MixedReality.Toolkit.Providers.WindowsMixedReality.Shared.cpp" } },
{ "pid": 1, "tid": 4, "ts": 1325792.23632813, "dur": 2448.49991798401, "ph": "X", "name": "HashCompilerInvocation", "args": { "durationMS": 2.44849991798401, "detail": "UnityEngine.PhysicsModule.cpp" } },
{ "pid": 1, "tid": 4, "ts": 1328275.26855469, "dur": 2266.29996299744, "ph": "X", "name": "HashCompilerInvocation", "args": { "durationMS": 2.26629996299744, "detail": "UnityEngine.Physics2DModule.cpp" } },
{ "pid": 1, "tid": 4, "ts": 1330581.66503906, "dur": 3019.99998092651, "ph": "X", "name": "HashCompilerInvocation", "args": { "durationMS": 3.01999998092651, "detail": "UnityEngine.VideoModule.cpp" } },
{ "pid": 1, "tid": 4, "ts": 1333633.17871094, "dur": 2061.10000610352, "ph": "X", "name": "HashCompilerInvocation", "args": { "durationMS": 2.06110000610352, "detail": "UnityEngine.VFXModule.cpp" } },
{ "pid": 1, "tid": 4, "ts": 1336826.90429688, "dur": 1247.4000453949, "ph": "X", "name": "HashCompilerInvocation", "args": { "durationMS": 1.2474000453949, "detail": "Microsoft.MixedReality.Toolkit.Services.InputSimulation_CodeGen.c" } },
{ "pid": 1, "tid": 4, "ts": 1338121.58203125, "dur": 3025.09999275208, "ph": "X", "name": "HashCompilerInvocation", "args": { "durationMS": 3.02509999275208, "detail": "System.Runtime.WindowsRuntime.UI.Xaml.cpp" } },
{ "pid": 1, "tid": 4, "ts": 1341197.50976563, "dur": 4522.09997177124, "ph": "X", "name": "HashCompilerInvocation", "args": { "durationMS": 4.52209997177124, "detail": "infback.c" } },
{ "pid": 1, "tid": 4, "ts": 1345880.61523438, "dur": 1886.70003414154, "ph": "X", "name": "HashCompilerInvocation", "args": { "durationMS": 1.88670003414154, "detail": "Microsoft.MixedReality.Toolkit.Services.TeleportSystem_CodeGen.c" } },
{ "pid": 1, "tid": 4, "ts": 1349000.9765625, "dur": 1836.40003204346, "ph": "X", "name": "HashCompilerInvocation", "args": { "durationMS": 1.83640003204346, "detail": "Microsoft.MixedReality.Toolkit.Services.CameraSystem_CodeGen.c" } },
{ "pid": 1, "tid": 4, "ts": 1350882.44628906, "dur": 5894.19984817505, "ph": "X", "name": "HashCompilerInvocation", "args": { "durationMS": 5.89419984817505, "detail": "Lump_libil2cpp_metadata.cpp" } },
{ "pid": 1, "tid": 4, "ts": 1356819.94628906, "dur": 1835.39998531342, "ph": "X", "name": "HashCompilerInvocation", "args": { "durationMS": 1.83539998531342, "detail": "Lump_libil2cpp_mono-runtime.cpp" } },
{ "pid": 1, "tid": 11, "ph": "M", "name": "thread_name", "args": { "name": "" } },
{ "pid": 1, "tid": 11, "ts": 1174023.80371094, "dur": 29696.6018676758, "ph": "X", "name": "HashCompilerInvocation", "args": { "durationMS": 29.6966018676758, "detail": "Il2CppCompilerCalculateTypeValues.cpp" } },
{ "pid": 1, "tid": 11, "ts": 1203759.39941406, "dur": 11476.300239563, "ph": "X", "name": "HashCompilerInvocation", "args": { "durationMS": 11.476300239563, "detail": "GenericMethods4.cpp" } },
{ "pid": 1, "tid": 11, "ts": 1215275.26855469, "dur": 10034.9998474121, "ph": "X", "name": "HashCompilerInvocation", "args": { "durationMS": 10.0349998474121, "detail": "Generics3.cpp" } },
{ "pid": 1, "tid": 11, "ts": 1225349.73144531, "dur": 12399.3997573853, "ph": "X", "name": "HashCompilerInvocation", "args": { "durationMS": 12.3993997573853, "detail": "Microsoft.MixedReality.Toolkit.cpp" } },
{ "pid": 1, "tid": 11, "ts": 1237790.28320313, "dur": 9521.30031585693, "ph": "X", "name": "HashCompilerInvocation", "args": { "durationMS": 9.52130031585693, "detail": "Generics1.cpp" } },
{ "pid": 1, "tid": 11, "ts": 1247360.59570313, "dur": 6849.99990463257, "ph": "X", "name": "HashCompilerInvocation", "args": { "durationMS": 6.84999990463257, "detail": "Generics46.cpp" } },
{ "pid": 1, "tid": 11, "ts": 1254250.85449219, "dur": 9051.6996383667, "ph": "X", "name": "HashCompilerInvocation", "args": { "durationMS": 9.0516996383667, "detail": "Il2CppComCallableWrappers22.cpp" } },
{ "pid": 1, "tid": 11, "ts": 1263345.21484375, "dur": 7242.40016937256, "ph": "X", "name": "HashCompilerInvocation", "args": { "durationMS": 7.24240016937256, "detail": "Il2CppComCallableWrappers17.cpp" } },
{ "pid": 1, "tid": 11, "ts": 1270628.05175781, "dur": 7486.10019683838, "ph": "X", "name": "HashCompilerInvocation", "args": { "durationMS": 7.48610019683838, "detail": "Il2CppComCallableWrappers.cpp" } },
{ "pid": 1, "tid": 11, "ts": 1278155.39550781, "dur": 5853.89995574951, "ph": "X", "name": "HashCompilerInvocation", "args": { "durationMS": 5.85389995574951, "detail": "Generics19.cpp" } },
{ "pid": 1, "tid": 11, "ts": 1284288.69628906, "dur": 9365.59963226318, "ph": "X", "name": "HashCompilerInvocation", "args": { "durationMS": 9.36559963226318, "detail": "Generics35.cpp" } },
{ "pid": 1, "tid": 11, "ts": 1293692.74902344, "dur": 6147.69983291626, "ph": "X", "name": "HashCompilerInvocation", "args": { "durationMS": 6.14769983291626, "detail": "Assembly-CSharp.cpp" } },
{ "pid": 1, "tid": 11, "ts": 1299879.27246094, "dur": 7134.90009307861, "ph": "X", "name": "HashCompilerInvocation", "args": { "durationMS": 7.13490009307861, "detail": "Generics14.cpp" } },
{ "pid": 1, "tid": 11, "ts": 1307052.49023438, "dur": 7366.70017242432, "ph": "X", "name": "HashCompilerInvocation", "args": { "durationMS": 7.36670017242432, "detail": "Generics21.cpp" } },
{ "pid": 1, "tid": 11, "ts": 1314460.20507813, "dur": 4284.59978103638, "ph": "X", "name": "HashCompilerInvocation", "args": { "durationMS": 4.28459978103638, "detail": "UnityEngine.IMGUIModule.cpp" } },
{ "pid": 1, "tid": 11, "ts": 1319489.37988281, "dur": 4651.29995346069, "ph": "X", "name": "HashCompilerInvocation", "args": { "durationMS": 4.65129995346069, "detail": "Microsoft.MixedReality.Toolkit.Services.InputSimulation.cpp" } },
{ "pid": 1, "tid": 11, "ts": 1324182.86132813, "dur": 3411.20004653931, "ph": "X", "name": "HashCompilerInvocation", "args": { "durationMS": 3.41120004653931, "detail": "System2.cpp" } },
{ "pid": 1, "tid": 11, "ts": 1327634.52148438, "dur": 1600.90005397797, "ph": "X", "name": "HashCompilerInvocation", "args": { "durationMS": 1.60090005397797, "detail": "System_CodeGen.c" } },
{ "pid": 1, "tid": 11, "ts": 1329272.58300781, "dur": 2879.10008430481, "ph": "X", "name": "HashCompilerInvocation", "args": { "durationMS": 2.87910008430481, "detail": "UnityEngine.AudioModule.cpp" } },
{ "pid": 1, "tid": 11, "ts": 1332530.02929688, "dur": 1434.20004844666, "ph": "X", "name": "HashCompilerInvocation", "args": { "durationMS": 1.43420004844666, "detail": "UnityEngine.TilemapModule.cpp" } },
{ "pid": 1, "tid": 11, "ts": 1334025.87890625, "dur": 3887.59994506836, "ph": "X", "name": "HashCompilerInvocation", "args": { "durationMS": 3.88759994506836, "detail": "UnityEngine.IMGUIModule_CodeGen.c" } },
{ "pid": 1, "tid": 11, "ts": 1337953.24707031, "dur": 2833.49990844727, "ph": "X", "name": "HashCompilerInvocation", "args": { "durationMS": 2.83349990844727, "detail": "xamarin_getifaddrs.c" } },
{ "pid": 1, "tid": 11, "ts": 1340833.37402344, "dur": 1788.10000419617, "ph": "X", "name": "HashCompilerInvocation", "args": { "durationMS": 1.78810000419617, "detail": "I18N.West_CodeGen.c" } },
{ "pid": 1, "tid": 11, "ts": 1342663.94042969, "dur": 2339.20001983643, "ph": "X", "name": "HashCompilerInvocation", "args": { "durationMS": 2.33920001983643, "detail": "gzwrite.c" } },
{ "pid": 1, "tid": 11, "ts": 1345050.78125, "dur": 5490.60010910034, "ph": "X", "name": "HashCompilerInvocation", "args": { "durationMS": 5.49060010910034, "detail": "inffast.c" } },
{ "pid": 1, "tid": 11, "ts": 1350572.87597656, "dur": 2561.80000305176, "ph": "X", "name": "HashCompilerInvocation", "args": { "durationMS": 2.56180000305176, "detail": "Microsoft.MixedReality.Toolkit.Services.BoundarySystem_CodeGen.c" } },
{ "pid": 1, "tid": 11, "ts": 1353180.17578125, "dur": 977.400004863739, "ph": "X", "name": "HashCompilerInvocation", "args": { "durationMS": 0.977400004863739, "detail": "UnityEngine.DirectorModule_CodeGen.c" } },
{ "pid": 1, "tid": 11, "ts": 1354204.46777344, "dur": 4321.59996032715, "ph": "X", "name": "HashCompilerInvocation", "args": { "durationMS": 4.32159996032715, "detail": "Lump_libil2cpp_mono.cpp" } },
{ "pid": 1, "tid": 13, "ph": "M", "name": "thread_name", "args": { "name": "" } },
{ "pid": 1, "tid": 13, "ts": 1174144.77539063, "dur": 28008.30078125, "ph": "X", "name": "HashCompilerInvocation", "args": { "durationMS": 28.00830078125, "detail": "Il2CppInteropDataTable.cpp" } },
{ "pid": 1, "tid": 13, "ts": 1202194.3359375, "dur": 11871.5000152588, "ph": "X", "name": "HashCompilerInvocation", "args": { "durationMS": 11.8715000152588, "detail": "GenericMethods2.cpp" } },
{ "pid": 1, "tid": 13, "ts": 1214114.99023438, "dur": 9691.39957427979, "ph": "X", "name": "HashCompilerInvocation", "args": { "durationMS": 9.69139957427979, "detail": "Unity.TextMeshPro.cpp" } },
{ "pid": 1, "tid": 13, "ts": 1223847.16796875, "dur": 8380.99956512451, "ph": "X", "name": "HashCompilerInvocation", "args": { "durationMS": 8.38099956512451, "detail": "Microsoft.MixedReality.Toolkit.Services.InputSystem.cpp" } },
{ "pid": 1, "tid": 13, "ts": 1232269.16503906, "dur": 17854.0992736816, "ph": "X", "name": "HashCompilerInvocation", "args": { "durationMS": 17.8540992736816, "detail": "mscorlib.cpp" } },
{ "pid": 1, "tid": 13, "ts": 1250163.57421875, "dur": 7428.69997024536, "ph": "X", "name": "HashCompilerInvocation", "args": { "durationMS": 7.42869997024536, "detail": "Il2CppComCallableWrappers10.cpp" } },
{ "pid": 1, "tid": 13, "ts": 1257629.63867188, "dur": 7670.80020904541, "ph": "X", "name": "HashCompilerInvocation", "args": { "durationMS": 7.67080020904541, "detail": "mscorlib4.cpp" } },
{ "pid": 1, "tid": 13, "ts": 1265343.62792969, "dur": 6562.30020523071, "ph": "X", "name": "HashCompilerInvocation", "args": { "durationMS": 6.56230020523071, "detail": "Generics41.cpp" } },
{ "pid": 1, "tid": 13, "ts": 1271946.65527344, "dur": 12918.7002182007, "ph": "X", "name": "HashCompilerInvocation", "args": { "durationMS": 12.9187002182007, "detail": "Il2CppComCallableWrappers14.cpp" } },
{ "pid": 1, "tid": 13, "ts": 1284912.59765625, "dur": 7870.1000213623, "ph": "X", "name": "HashCompilerInvocation", "args": { "durationMS": 7.8701000213623, "detail": "Il2CppProjectedComCallableWrapperMethods4.cpp" } },
{ "pid": 1, "tid": 13, "ts": 1292834.35058594, "dur": 9450.90007781982, "ph": "X", "name": "HashCompilerInvocation", "args": { "durationMS": 9.45090007781982, "detail": "Il2CppComCallableWrappers3.cpp" } },
{ "pid": 1, "tid": 13, "ts": 1302332.64160156, "dur": 6710.29996871948, "ph": "X", "name": "HashCompilerInvocation", "args": { "durationMS": 6.71029996871948, "detail": "Generics4.cpp" } },
{ "pid": 1, "tid": 13, "ts": 1309087.15820313, "dur": 7229.70008850098, "ph": "X", "name": "HashCompilerInvocation", "args": { "durationMS": 7.22970008850098, "detail": "Generics27.cpp" } },
{ "pid": 1, "tid": 13, "ts": 1316357.78808594, "dur": 3832.200050354, "ph": "X", "name": "HashCompilerInvocation", "args": { "durationMS": 3.832200050354, "detail": "Il2CppCompilerCalculateTypeValuesTable.cpp" } },
{ "pid": 1, "tid": 13, "ts": 1320730.83496094, "dur": 4485.89992523193, "ph": "X", "name": "HashCompilerInvocation", "args": { "durationMS": 4.48589992523193, "detail": "I18N.Rare1.cpp" } },
{ "pid": 1, "tid": 13, "ts": 1325258.91113281, "dur": 2818.9001083374, "ph": "X", "name": "HashCompilerInvocation", "args": { "durationMS": 2.8189001083374, "detail": "UnityEngine.TextCoreModule.cpp" } },
{ "pid": 1, "tid": 13, "ts": 1328113.52539063, "dur": 4030.00020980835, "ph": "X", "name": "HashCompilerInvocation", "args": { "durationMS": 4.03000020980835, "detail": "UnityEngine.UI3.cpp" } },
{ "pid": 1, "tid": 13, "ts": 1332523.68164063, "dur": 1440.99998474121, "ph": "X", "name": "HashCompilerInvocation", "args": { "durationMS": 1.44099998474121, "detail": "deflate.c" } },
{ "pid": 1, "tid": 13, "ts": 1334038.57421875, "dur": 3316.99991226196, "ph": "X", "name": "HashCompilerInvocation", "args": { "durationMS": 3.31699991226196, "detail": "I18N.CJK_CodeGen.c" } },
{ "pid": 1, "tid": 13, "ts": 1337393.43261719, "dur": 1429.00002002716, "ph": "X", "name": "HashCompilerInvocation", "args": { "durationMS": 1.42900002002716, "detail": "UnityEngine.AssetBundleModule.cpp" } },
{ "pid": 1, "tid": 13, "ts": 1338864.99023438, "dur": 2805.39989471436, "ph": "X", "name": "HashCompilerInvocation", "args": { "durationMS": 2.80539989471436, "detail": "System.Core_CodeGen.c" } },
{ "pid": 1, "tid": 13, "ts": 1341707.27539063, "dur": 1278.49996089935, "ph": "X", "name": "HashCompilerInvocation", "args": { "durationMS": 1.27849996089935, "detail": "I18N.Other_CodeGen.c" } },
{ "pid": 1, "tid": 13, "ts": 1343038.33007813, "dur": 2654.50000762939, "ph": "X", "name": "HashCompilerInvocation", "args": { "durationMS": 2.65450000762939, "detail": "UnityEngine.AudioModule_CodeGen.c" } },
{ "pid": 1, "tid": 13, "ts": 1345728.515625, "dur": 1854.50005531311, "ph": "X", "name": "HashCompilerInvocation", "args": { "durationMS": 1.85450005531311, "detail": "System.Numerics_CodeGen.c" } },
{ "pid": 1, "tid": 13, "ts": 1347620.97167969, "dur": 2849.69997406006, "ph": "X", "name": "HashCompilerInvocation", "args": { "durationMS": 2.84969997406006, "detail": "DOTweenPro_CodeGen.c" } },
{ "pid": 1, "tid": 13, "ts": 1350503.54003906, "dur": 4330.80005645752, "ph": "X", "name": "HashCompilerInvocation", "args": { "durationMS": 4.33080005645752, "detail": "gc.c" } },
{ "pid": 1, "tid": 13, "ts": 1354861.20605469, "dur": 2619.40002441406, "ph": "X", "name": "HashCompilerInvocation", "args": { "durationMS": 2.61940002441406, "detail": "Lump_libil2cpp_vm-utils.cpp" } },
{ "pid": 1, "tid": 13, "ts": 1357530.63964844, "dur": 1060.40000915527, "ph": "X", "name": "HashCompilerInvocation", "args": { "durationMS": 1.06040000915527, "detail": "class-internals.cpp" } },
{ "pid": 1, "tid": 14, "ph": "M", "name": "thread_name", "args": { "name": "" } },
{ "pid": 1, "tid": 14, "ts": 1174333.86230469, "dur": 25529.9015045166, "ph": "X", "name": "HashCompilerInvocation", "args": { "durationMS": 25.5299015045166, "detail": "Il2CppCompilerCalculateTypeValues2.cpp" } },
{ "pid": 1, "tid": 14, "ts": 1199980.71289063, "dur": 11975.0003814697, "ph": "X", "name": "HashCompilerInvocation", "args": { "durationMS": 11.9750003814697, "detail": "Unity.TextMeshPro1.cpp" } },
{ "pid": 1, "tid": 14, "ts": 1211994.87304688, "dur": 9133.99982452393, "ph": "X", "name": "HashCompilerInvocation", "args": { "durationMS": 9.13399982452393, "detail": "Microsoft.MixedReality.Toolkit.SDK4.cpp" } },
{ "pid": 1, "tid": 14, "ts": 1221166.87011719, "dur": 8725.70037841797, "ph": "X", "name": "HashCompilerInvocation", "args": { "durationMS": 8.72570037841797, "detail": "Generics38.cpp" } },
{ "pid": 1, "tid": 14, "ts": 1229939.57519531, "dur": 8662.59956359863, "ph": "X", "name": "HashCompilerInvocation", "args": { "durationMS": 8.66259956359863, "detail": "GenericMethods8.cpp" } },
{ "pid": 1, "tid": 14, "ts": 1238641.96777344, "dur": 8591.09973907471, "ph": "X", "name": "HashCompilerInvocation", "args": { "durationMS": 8.59109973907471, "detail": "Generics45.cpp" } },
{ "pid": 1, "tid": 14, "ts": 1247275.51269531, "dur": 7000, "ph": "X", "name": "HashCompilerInvocation", "args": { "durationMS": 7, "detail": "Il2CppComCallableWrappers1.cpp" } },
{ "pid": 1, "tid": 14, "ts": 1254322.75390625, "dur": 7283.80012512207, "ph": "X", "name": "HashCompilerInvocation", "args": { "durationMS": 7.28380012512207, "detail": "Generics8.cpp" } },
{ "pid": 1, "tid": 14, "ts": 1261657.10449219, "dur": 7436.69986724854, "ph": "X", "name": "HashCompilerInvocation", "args": { "durationMS": 7.43669986724854, "detail": "Il2CppComCallableWrappers21.cpp" } },
{ "pid": 1, "tid": 14, "ts": 1269130.24902344, "dur": 6652.10008621216, "ph": "X", "name": "HashCompilerInvocation", "args": { "durationMS": 6.65210008621216, "detail": "Generics24.cpp" } },
{ "pid": 1, "tid": 14, "ts": 1275817.26074219, "dur": 7314.4998550415, "ph": "X", "name": "HashCompilerInvocation", "args": { "durationMS": 7.3144998550415, "detail": "Il2CppComCallableWrappers12.cpp" } },
{ "pid": 1, "tid": 14, "ts": 1283172.8515625, "dur": 6321.59996032715, "ph": "X", "name": "HashCompilerInvocation", "args": { "durationMS": 6.32159996032715, "detail": "Il2CppComCallableWrappers13.cpp" } },
{ "pid": 1, "tid": 14, "ts": 1289533.69140625, "dur": 6453.10020446777, "ph": "X", "name": "HashCompilerInvocation", "args": { "durationMS": 6.45310020446777, "detail": "Generics10.cpp" } },
{ "pid": 1, "tid": 14, "ts": 1296023.07128906, "dur": 6997.00021743774, "ph": "X", "name": "HashCompilerInvocation", "args": { "durationMS": 6.99700021743774, "detail": "Generics13.cpp" } },
{ "pid": 1, "tid": 14, "ts": 1303066.16210938, "dur": 10101.900100708, "ph": "X", "name": "HashCompilerInvocation", "args": { "durationMS": 10.101900100708, "detail": "Il2CppProjectedComCallableWrapperMethods3.cpp" } },
{ "pid": 1, "tid": 14, "ts": 1313209.59472656, "dur": 4837.1000289917, "ph": "X", "name": "HashCompilerInvocation", "args": { "durationMS": 4.8371000289917, "detail": "Microsoft.MixedReality.Toolkit.SDK6.cpp" } },
{ "pid": 1, "tid": 14, "ts": 1318090.94238281, "dur": 4160.39991378784, "ph": "X", "name": "HashCompilerInvocation", "args": { "durationMS": 4.16039991378784, "detail": "DOTween1.cpp" } },
{ "pid": 1, "tid": 14, "ts": 1322284.05761719, "dur": 2922.49989509583, "ph": "X", "name": "HashCompilerInvocation", "args": { "durationMS": 2.92249989509583, "detail": "char-conversions.cpp" } },
{ "pid": 1, "tid": 14, "ts": 1325251.22070313, "dur": 2995.30005455017, "ph": "X", "name": "HashCompilerInvocation", "args": { "durationMS": 2.99530005455017, "detail": "Microsoft.MixedReality.Toolkit.Async.cpp" } },
{ "pid": 1, "tid": 14, "ts": 1328271.484375, "dur": 1894.50001716614, "ph": "X", "name": "HashCompilerInvocation", "args": { "durationMS": 1.89450001716614, "detail": "UnityEngine.SharedInternalsModule.cpp" } },
{ "pid": 1, "tid": 14, "ts": 1330200.92773438, "dur": 5484.00020599365, "ph": "X", "name": "HashCompilerInvocation", "args": { "durationMS": 5.48400020599365, "detail": "DOTween43.cpp" } },
{ "pid": 1, "tid": 14, "ts": 1336806.03027344, "dur": 1251.29997730255, "ph": "X", "name": "HashCompilerInvocation", "args": { "durationMS": 1.25129997730255, "detail": "UnityEngine.JSONSerializeModule.cpp" } },
{ "pid": 1, "tid": 14, "ts": 1338107.91015625, "dur": 6991.30010604858, "ph": "X", "name": "HashCompilerInvocation", "args": { "durationMS": 6.99130010604858, "detail": "UnityEngine.TextCoreModule_CodeGen.c" } },
{ "pid": 1, "tid": 14, "ts": 1345144.65332031, "dur": 2213.50002288818, "ph": "X", "name": "HashCompilerInvocation", "args": { "durationMS": 2.21350002288818, "detail": "I18N.MidEast_CodeGen.c" } },
{ "pid": 1, "tid": 14, "ts": 1347401.00097656, "dur": 2488.39998245239, "ph": "X", "name": "HashCompilerInvocation", "args": { "durationMS": 2.48839998245239, "detail": "UnityEngine.UIElementsModule_CodeGen.c" } },
{ "pid": 1, "tid": 14, "ts": 1349935.18066406, "dur": 1078.40001583099, "ph": "X", "name": "HashCompilerInvocation", "args": { "durationMS": 1.07840001583099, "detail": "DOTween43_CodeGen.c" } },
{ "pid": 1, "tid": 14, "ts": 1351042.23632813, "dur": 2669.89994049072, "ph": "X", "name": "HashCompilerInvocation", "args": { "durationMS": 2.66989994049072, "detail": "System.Runtime.WindowsRuntime.UI.Xaml_CodeGen.c" } },
{ "pid": 1, "tid": 14, "ts": 1353743.28613281, "dur": 1533.10000896454, "ph": "X", "name": "HashCompilerInvocation", "args": { "durationMS": 1.53310000896454, "detail": "System.Numerics.Vectors.cpp" } },
{ "pid": 1, "tid": 14, "ts": 1355310.91308594, "dur": 3215.19994735718, "ph": "X", "name": "HashCompilerInvocation", "args": { "durationMS": 3.21519994735718, "detail": "System.Numerics.Vectors_CodeGen.c" } }
],
"meta_datetime": "11/11/2020 17:18:14",
"meta_command_line": "\"E:\\Graduate\\Graduate Design\\GitHub\\CSAR\\CSAR Simulation\\Build\\06\\Il2CppOutputProject\\\\IL2CPP\\build\\il2cpp.exe\"  --libil2cpp-static --compile-cpp -architecture=ARM64 -configuration=Release -platform=winrt -outputpath=\"E:\\Graduate\\Graduate Design\\GitHub\\CSAR\\CSAR Simulation\\Build\\06\\\\build\\bin\\ARM64\\Release\\GameAssembly.dll\" --data-folder=\"E:\\Graduate\\Graduate Design\\GitHub\\CSAR\\CSAR Simulation\\Build\\06\\\\build\\bin\\ARM64\\Release\\\\\" -cachedirectory=\"E:\\Graduate\\Graduate Design\\GitHub\\CSAR\\CSAR Simulation\\Build\\06\\\\build\\obj\\il2cppOutputProject\\ARM64\\Release\\\\\" -generatedcppdir=\"E:\\Graduate\\Graduate Design\\GitHub\\CSAR\\CSAR Simulation\\Build\\06\\Il2CppOutputProject\\\\Source\"  --profiler-report --additional-defines=WINDOWS_UWP --additional-defines=UNITY_UWP --additional-defines=UNITY_WSA_10_0 --additional-defines=UNITY_WSA --additional-defines=UNITY_WINRT --additional-defines=PLATFORM_WINRT -dotnetprofile=unityaot -verbose --map-file-parser=\"E:\\Graduate\\Graduate Design\\GitHub\\CSAR\\CSAR Simulation\\Build\\06\\Il2CppOutputProject\\\\IL2CPP\\MapFileParser\\MapFileParser.exe\"",
"meta_command_line_args": "E:\\Graduate\\Graduate Design\\GitHub\\CSAR\\CSAR Simulation\\Build\\06\\Il2CppOutputProject\\\\IL2CPP\\build\\il2cpp.exe --libil2cpp-static --compile-cpp -architecture=ARM64 -configuration=Release -platform=winrt -outputpath=E:\\Graduate\\Graduate Design\\GitHub\\CSAR\\CSAR Simulation\\Build\\06\\\\build\\bin\\ARM64\\Release\\GameAssembly.dll --data-folder=E:\\Graduate\\Graduate Design\\GitHub\\CSAR\\CSAR Simulation\\Build\\06\\\\build\\bin\\ARM64\\Release\\ -cachedirectory=E:\\Graduate\\Graduate Design\\GitHub\\CSAR\\CSAR Simulation\\Build\\06\\\\build\\obj\\il2cppOutputProject\\ARM64\\Release\\ -generatedcppdir=E:\\Graduate\\Graduate Design\\GitHub\\CSAR\\CSAR Simulation\\Build\\06\\Il2CppOutputProject\\\\Source --profiler-report --additional-defines=WINDOWS_UWP --additional-defines=UNITY_UWP --additional-defines=UNITY_WSA_10_0 --additional-defines=UNITY_WSA --additional-defines=UNITY_WINRT --additional-defines=PLATFORM_WINRT -dotnetprofile=unityaot -verbose --map-file-parser=E:\\Graduate\\Graduate Design\\GitHub\\CSAR\\CSAR Simulation\\Build\\06\\Il2CppOutputProject\\\\IL2CPP\\MapFileParser\\MapFileParser.exe",
"meta_user_name": "jx199",
"meta_os_version": "Microsoft Windows NT 6.2.9200.0",
"meta_cpu_count": "12"}
